Workbook

Sheet Summary
B1: Sales Pipeline Report
B2: ="All open deals as of "&TEXT(Settings!B3,"dd mmm yyyy")&" | values in GBP" -> All open deals as of 17 Sep 2026 | values in GBP
B4: OPEN DEALS | D4: PIPELINE VALUE | H4: WEIGHTED VALUE | J4: NEW BUSINESS (£)
B5: =COUNTA('Open Deals'!$B$2:$B$130) -> 129 | D5: =SUM('Open Deals'!$I$2:$I$130) -> 7430747 | H5: =SUM('Open Deals'!$K$2:$K$130) -> 4352051.7 | J5: =SUMIF('Open Deals'!$E$2:$E$130,"New business",'Open Deals'!$I$2:$I$130) -> 2955200
B8: Pipeline by stage | H8: Pipeline by Account Owner
B9: Stage | C9: Deals | D9: Probability % | E9: Value (£) | F9: Weighted (£) | H9: Account Owner | I9: Deals | J9: Value (£) | K9: Weighted (£)
B10: Understand Need/Problem | C10: =COUNTIF('Open Deals'!$F$2:$F$130,B10) -> 33 | D10: =INDEX(Settings!$C$11:$C$16,MATCH(B10,Settings!$A$11:$A$16,0)) -> 0.45 | E10: =SUMIF('Open Deals'!$F$2:$F$130,B10,'Open Deals'!$I$2:$I$130) -> 1586687 | F10: =SUMIF('Open Deals'!$F$2:$F$130,B10,'Open Deals'!$K$2:$K$130) -> 714009.15 | H10: Valeriia Mukhai | I10: =COUNTIF('Open Deals'!$C$2:$C$130,H10) -> 50 | J10: =SUMIF('Open Deals'!$C$2:$C$130,H10,'Open Deals'!$I$2:$I$130) -> 3332010 | K10: =SUMIF('Open Deals'!$C$2:$C$130,H10,'Open Deals'!$K$2:$K$130) -> 1918792.5
B11: Create Proposal | C11: =COUNTIF('Open Deals'!$F$2:$F$130,B11) -> 21 | D11: =INDEX(Settings!$C$11:$C$16,MATCH(B11,Settings!$A$11:$A$16,0)) -> 0.5 | E11: =SUMIF('Open Deals'!$F$2:$F$130,B11,'Open Deals'!$I$2:$I$130) -> 1409150 | F11: =SUMIF('Open Deals'!$F$2:$F$130,B11,'Open Deals'!$K$2:$K$130) -> 704575 | H11: Ritchie Boubouli | I11: =COUNTIF('Open Deals'!$C$2:$C$130,H11) -> 40 | J11: =SUMIF('Open Deals'!$C$2:$C$130,H11,'Open Deals'!$I$2:$I$130) -> 2249937 | K11: =SUMIF('Open Deals'!$C$2:$C$130,H11,'Open Deals'!$K$2:$K$130) -> 1242859.1
B12: Present Proposal | C12: =COUNTIF('Open Deals'!$F$2:$F$130,B12) -> 12 | D12: =INDEX(Settings!$C$11:$C$16,MATCH(B12,Settings!$A$11:$A$16,0)) -> 0.55 | E12: =SUMIF('Open Deals'!$F$2:$F$130,B12,'Open Deals'!$I$2:$I$130) -> 991590 | F12: =SUMIF('Open Deals'!$F$2:$F$130,B12,'Open Deals'!$K$2:$K$130) -> 545374.5 | H12: Carrick Klopper | I12: =COUNTIF('Open Deals'!$C$2:$C$130,H12) -> 39 | J12: =SUMIF('Open Deals'!$C$2:$C$130,H12,'Open Deals'!$I$2:$I$130) -> 1848800 | K12: =SUMIF('Open Deals'!$C$2:$C$130,H12,'Open Deals'!$K$2:$K$130) -> 1190400
B13: Feedback | C13: =COUNTIF('Open Deals'!$F$2:$F$130,B13) -> 28 | D13: =INDEX(Settings!$C$11:$C$16,MATCH(B13,Settings!$A$11:$A$16,0)) -> 0.6 | E13: =SUMIF('Open Deals'!$F$2:$F$130,B13,'Open Deals'!$I$2:$I$130) -> 1803900 | F13: =SUMIF('Open Deals'!$F$2:$F$130,B13,'Open Deals'!$K$2:$K$130) -> 1082340 | H13: Total | I13: =SUM(I10:I12) -> 129 | J13: =SUM(J10:J12) -> 7430747 | K13: =SUM(K10:K12) -> 4352051.7
B14: Negotiation | C14: =COUNTIF('Open Deals'!$F$2:$F$130,B14) -> 23 | D14: =INDEX(Settings!$C$11:$C$16,MATCH(B14,Settings!$A$11:$A$16,0)) -> 0.75 | E14: =SUMIF('Open Deals'!$F$2:$F$130,B14,'Open Deals'!$I$2:$I$130) -> 877540 | F14: =SUMIF('Open Deals'!$F$2:$F$130,B14,'Open Deals'!$K$2:$K$130) -> 658155
B15: IO Sent Out | C15: =COUNTIF('Open Deals'!$F$2:$F$130,B15) -> 12 | D15: =INDEX(Settings!$C$11:$C$16,MATCH(B15,Settings!$A$11:$A$16,0)) -> 0.85 | E15: =SUMIF('Open Deals'!$F$2:$F$130,B15,'Open Deals'!$I$2:$I$130) -> 761880 | F15: =SUMIF('Open Deals'!$F$2:$F$130,B15,'Open Deals'!$K$2:$K$130) -> 647598
B16: Total | C16: =SUM(C10:C15) -> 129 | D16: =IF(E16=0,0,F16/E16) -> 0.58568158 | E16: =SUM(E10:E15) -> 7430747 | F16: =SUM(F10:F15) -> 4352051.7
B19: Pipeline by Account Manager | H19: Pipeline by industry
B20: Account Manager | C20: Deals | D20: Value (£) | E20: Weighted (£) | H20: Industry | I20: Deals | J20: Value (£) | K20: Weighted (£)
B21: Maggie Parrott | C21: =COUNTIF('Open Deals'!$D$2:$D$130,B21) -> 16 | D21: =SUMIF('Open Deals'!$D$2:$D$130,B21,'Open Deals'!$I$2:$I$130) -> 998910 | E21: =SUMIF('Open Deals'!$D$2:$D$130,B21,'Open Deals'!$K$2:$K$130) -> 588396.5 | H21: CPG | I21: =COUNTIF('Open Deals'!$P$2:$P$130,H21) -> 43 | J21: =SUMIF('Open Deals'!$P$2:$P$130,H21,'Open Deals'!$I$2:$I$130) -> 2165160 | K21: =SUMIF('Open Deals'!$P$2:$P$130,H21,'Open Deals'!$K$2:$K$130) -> 1314135
B22: Emma-Leigh Pedder | C22: =COUNTIF('Open Deals'!$D$2:$D$130,B22) -> 10 | D22: =SUMIF('Open Deals'!$D$2:$D$130,B22,'Open Deals'!$I$2:$I$130) -> 923440 | E22: =SUMIF('Open Deals'!$D$2:$D$130,B22,'Open Deals'!$K$2:$K$130) -> 534010 | H22: Tech | I22: =COUNTIF('Open Deals'!$P$2:$P$130,H22) -> 29 | J22: =SUMIF('Open Deals'!$P$2:$P$130,H22,'Open Deals'!$I$2:$I$130) -> 1784700 | K22: =SUMIF('Open Deals'!$P$2:$P$130,H22,'Open Deals'!$K$2:$K$130) -> 1102530
B23: Lucia Lopez Moreno | C23: =COUNTIF('Open Deals'!$D$2:$D$130,B23) -> 14 | D23: =SUMIF('Open Deals'!$D$2:$D$130,B23,'Open Deals'!$I$2:$I$130) -> 885037 | E23: =SUMIF('Open Deals'!$D$2:$D$130,B23,'Open Deals'!$K$2:$K$130) -> 558986.65 | H23: Finance | I23: =COUNTIF('Open Deals'!$P$2:$P$130,H23) -> 13 | J23: =SUMIF('Open Deals'!$P$2:$P$130,H23,'Open Deals'!$I$2:$I$130) -> 926087 | K23: =SUMIF('Open Deals'!$P$2:$P$130,H23,'Open Deals'!$K$2:$K$130) -> 521221.65
B24: Levi Hoang | C24: =COUNTIF('Open Deals'!$D$2:$D$130,B24) -> 11 | D24: =SUMIF('Open Deals'!$D$2:$D$130,B24,'Open Deals'!$I$2:$I$130) -> 555600 | E24: =SUMIF('Open Deals'!$D$2:$D$130,B24,'Open Deals'!$K$2:$K$130) -> 331365 | H24: Automotive | I24: =COUNTIF('Open Deals'!$P$2:$P$130,H24) -> 1 | J24: =SUMIF('Open Deals'!$P$2:$P$130,H24,'Open Deals'!$I$2:$I$130) -> 740000 | K24: =SUMIF('Open Deals'!$P$2:$P$130,H24,'Open Deals'!$K$2:$K$130) -> 370000
B25: Sarineh Garapetian | C25: =COUNTIF('Open Deals'!$D$2:$D$130,B25) -> 6 | D25: =SUMIF('Open Deals'!$D$2:$D$130,B25,'Open Deals'!$I$2:$I$130) -> 281750 | E25: =SUMIF('Open Deals'!$D$2:$D$130,B25,'Open Deals'!$K$2:$K$130) -> 161887.5 | H25: Healthcare | I25: =COUNTIF('Open Deals'!$P$2:$P$130,H25) -> 9 | J25: =SUMIF('Open Deals'!$P$2:$P$130,H25,'Open Deals'!$I$2:$I$130) -> 403500 | K25: =SUMIF('Open Deals'!$P$2:$P$130,H25,'Open Deals'!$K$2:$K$130) -> 246170
B26: Blake Hoang | C26: =COUNTIF('Open Deals'!$D$2:$D$130,B26) -> 2 | D26: =SUMIF('Open Deals'!$D$2:$D$130,B26,'Open Deals'!$I$2:$I$130) -> 51800 | E26: =SUMIF('Open Deals'!$D$2:$D$130,B26,'Open Deals'!$K$2:$K$130) -> 29970 | H26: Travel & Telecom | I26: =COUNTIF('Open Deals'!$P$2:$P$130,H26) -> 8 | J26: =SUMIF('Open Deals'!$P$2:$P$130,H26,'Open Deals'!$I$2:$I$130) -> 361800 | K26: =SUMIF('Open Deals'!$P$2:$P$130,H26,'Open Deals'!$K$2:$K$130) -> 218440
B27: Total | C27: =SUM(C21:C26) -> 59 | D27: =SUM(D21:D26) -> 3696537 | E27: =SUM(E21:E26) -> 2204615.6 | H27: Food & Beverage | I27: =COUNTIF('Open Deals'!$P$2:$P$130,H27) -> 6 | J27: =SUMIF('Open Deals'!$P$2:$P$130,H27,'Open Deals'!$I$2:$I$130) -> 264600 | K27: =SUMIF('Open Deals'!$P$2:$P$130,H27,'Open Deals'!$K$2:$K$130) -> 133780
H28: Entertainment | I28: =COUNTIF('Open Deals'!$P$2:$P$130,H28) -> 6 | J28: =SUMIF('Open Deals'!$P$2:$P$130,H28,'Open Deals'!$I$2:$I$130) -> 261100 | K28: =SUMIF('Open Deals'!$P$2:$P$130,H28,'Open Deals'!$K$2:$K$130) -> 162485
H29: Retail | I29: =COUNTIF('Open Deals'!$P$2:$P$130,H29) -> 5 | J29: =SUMIF('Open Deals'!$P$2:$P$130,H29,'Open Deals'!$I$2:$I$130) -> 248400 | K29: =SUMIF('Open Deals'!$P$2:$P$130,H29,'Open Deals'!$K$2:$K$130) -> 142710
H30: Health & Wellness | I30: =COUNTIF('Open Deals'!$P$2:$P$130,H30) -> 4 | J30: =SUMIF('Open Deals'!$P$2:$P$130,H30,'Open Deals'!$I$2:$I$130) -> 127000 | K30: =SUMIF('Open Deals'!$P$2:$P$130,H30,'Open Deals'!$K$2:$K$130) -> 60480
H31: Hospitality | I31: =COUNTIF('Open Deals'!$P$2:$P$130,H31) -> 2 | J31: =SUMIF('Open Deals'!$P$2:$P$130,H31,'Open Deals'!$I$2:$I$130) -> 37000 | K31: =SUMIF('Open Deals'!$P$2:$P$130,H31,'Open Deals'!$K$2:$K$130) -> 16650
H32: Total | I32: =SUM(I21:I31) -> 126 | J32: =SUM(J21:J31) -> 7319347 | K32: =SUM(K21:K31) -> 4288601.7
B34: Charts

Sheet Open Deals
A1: Brand | B1: Deal | C1: Account Owner | D1: Account Manager | E1: Client status | F1: Stage | G1: Value | H1: Currency | I1: Value (£) | J1: Probability | K1: Weighted (£) | L1: Expected close | M1: Days in stage | N1: Deal added | O1: Main contact | P1: Industry | Q1: Sub-industry | R1: Website
A2: Runway | B2: Runway - SOW2 / EOY | C2: Valeriia Mukhai | D2: Emma-Leigh Pedder | E2: Existing client | F2: IO Sent Out | G2: 300000 | H2: USD | I2: =G2*INDEX(Settings!$B$6:$B$8,MATCH(H2,Settings!$A$6:$A$8,0)) -> 222000 | J2: =INDEX(Settings!$C$11:$C$16,MATCH(F2,Settings!$A$11:$A$16,0)) -> 0.85 | K2: =I2*J2 -> 188700 | L2: 46295 | M2: =Settings!$B$3-DATE(2026,9,4) -> 13 | N2: 46252 | O2: Julia Martins | P2: Tech | Q2: AI Video | R2: runwayml.com
A3: Oreate AI | B3: Oreate AI LATAM Q4 SOW 4 - SEP 26 | C3: Carrick Klopper | D3: Lucia Lopez Moreno | E3: Existing client | F3: IO Sent Out | G3: 150000 | H3: USD | I3: =G3*INDEX(Settings!$B$6:$B$8,MATCH(H3,Settings!$A$6:$A$8,0)) -> 111000 | J3: =INDEX(Settings!$C$11:$C$16,MATCH(F3,Settings!$A$11:$A$16,0)) -> 0.85 | K3: =I3*J3 -> 94350 | L3: 46295 | M3: =Settings!$B$3-DATE(2026,9,10) -> 7 | N3: 46253 | O3: Raul Tang | P3: Tech | Q3: AI | R3: oreateai.com
A4: ILSO | B4: ILSO - Prime Day + Black Friday US / Oct-Nov 2026 | C4: Valeriia Mukhai | D4: - | E4: Existing client | F4: IO Sent Out | G4: 100000 | H4: USD | I4: =G4*INDEX(Settings!$B$6:$B$8,MATCH(H4,Settings!$A$6:$A$8,0)) -> 74000 | J4: =INDEX(Settings!$C$11:$C$16,MATCH(F4,Settings!$A$11:$A$16,0)) -> 0.85 | K4: =I4*J4 -> 62900 | L4: 46295 | M4: =Settings!$B$3-DATE(2026,9,11) -> 6 | N4: 46275 | O4: Poya Chang | P4: CPG | Q4: Korean Beauty | R4: milip.kr
A5: Comfort Click | B5: Comfort Click Q4 SOW 2 - SEP 26 | C5: Carrick Klopper | D5: - | E5: Existing client | F5: IO Sent Out | G5: 60000 | H5: GBP | I5: =G5*INDEX(Settings!$B$6:$B$8,MATCH(H5,Settings!$A$6:$A$8,0)) -> 60000 | J5: =INDEX(Settings!$C$11:$C$16,MATCH(F5,Settings!$A$11:$A$16,0)) -> 0.85 | K5: =I5*J5 -> 51000 | L5: 46295 | M5: =Settings!$B$3-DATE(2026,8,24) -> 24 | N5: 46156 | O5: Prateek Tyagi | P5: Tech | Q5: Smart Home | R5: comfortclick.co.uk
A6: Oreate AI | B6: Oreate AI - LATAM - SOW 2 - AUG 26 | C6: Carrick Klopper | D6: Lucia Lopez Moreno | E6: Existing client | F6: IO Sent Out | G6: 75000 | H6: USD | I6: =G6*INDEX(Settings!$B$6:$B$8,MATCH(H6,Settings!$A$6:$A$8,0)) -> 55500 | J6: =INDEX(Settings!$C$11:$C$16,MATCH(F6,Settings!$A$11:$A$16,0)) -> 0.85 | K6: =I6*J6 -> 47175 | L6: 46283 | M6: =Settings!$B$3-DATE(2026,8,19) -> 29 | N6: 46223 | O6: Raul Tang | P6: Tech | Q6: AI | R6: oreateai.com
A7: SEB | B7: SEB x WMF Coffee Machine x Nov 2026 | C7: Ritchie Boubouli | D7: Sarineh Garapetian | E7: Existing client | F7: IO Sent Out | G7: 60000 | H7: EUR | I7: =G7*INDEX(Settings!$B$6:$B$8,MATCH(H7,Settings!$A$6:$A$8,0)) -> 51000 | J7: =INDEX(Settings!$C$11:$C$16,MATCH(F7,Settings!$A$11:$A$16,0)) -> 0.85 | K7: =I7*J7 -> 43350 | L7: 46311 | M7: =Settings!$B$3-DATE(2026,7,17) -> 62 | N7: 46148 | O7: Paulina Gardunorubi | P7: CPG | Q7: Home Appliances | R7: groupeseb.com
A8: Medihealcos | B8: Mediheal UK / Black Friday 16th Nov | C8: Valeriia Mukhai | D8: - | E8: Existing client | F8: IO Sent Out | G8: 50000 | H8: GBP | I8: =G8*INDEX(Settings!$B$6:$B$8,MATCH(H8,Settings!$A$6:$A$8,0)) -> 50000 | J8: =INDEX(Settings!$C$11:$C$16,MATCH(F8,Settings!$A$11:$A$16,0)) -> 0.85 | K8: =I8*J8 -> 42500 | L8: 46295 | M8: =Settings!$B$3-DATE(2026,9,16) -> 1 | N8: 46275 | O8: hwjang | P8: CPG | Q8: Korean Beauty | R8: mediheal.com
A9: Myungin Cosmetics (Farmstay / Anotherface / Laferme) | B9: Myungin - Scope B / Amazon + Instagram creators (Farmstay, Anotherface, Laferme) Sept–Dec 2026 | C9: Valeriia Mukhai | D9: - | E9: New business | F9: IO Sent Out | G9: 60000 | H9: USD | I9: =G9*INDEX(Settings!$B$6:$B$8,MATCH(H9,Settings!$A$6:$A$8,0)) -> 44400 | J9: =INDEX(Settings!$C$11:$C$16,MATCH(F9,Settings!$A$11:$A$16,0)) -> 0.85 | K9: =I9*J9 -> 37740 | L9: 46289 | M9: =Settings!$B$3-DATE(2026,9,17) -> 0 | N9: 46282 | O9: Seonlim Lee | P9: CPG | Q9: Korean Beauty
A10: AvaTrade | B10: AvaTrade x Conversion Influencer Campaign Test x Sept 2026 | C10: Ritchie Boubouli | D10: Lucia Lopez Moreno | E10: Existing client | F10: IO Sent Out | G10: 45000 | H10: USD | I10: =G10*INDEX(Settings!$B$6:$B$8,MATCH(H10,Settings!$A$6:$A$8,0)) -> 33300 | J10: =INDEX(Settings!$C$11:$C$16,MATCH(F10,Settings!$A$11:$A$16,0)) -> 0.85 | K10: =I10*J10 -> 28305 | L10: 46277 | M10: =Settings!$B$3-DATE(2026,8,28) -> 20 | N10: 46224 | O10: Nicolas Embon | P10: Finance | Q10: Online Trading | R10: avatrade.com
A11: Amorepacific | B11: Illiyoon BY27 (12months)- AmorePacific | C11: Valeriia Mukhai | D11: Maggie Parrott | E11: Existing client | F11: IO Sent Out | G11: 43000 | H11: USD | I11: =G11*INDEX(Settings!$B$6:$B$8,MATCH(H11,Settings!$A$6:$A$8,0)) -> 31820 | J11: =INDEX(Settings!$C$11:$C$16,MATCH(F11,Settings!$A$11:$A$16,0)) -> 0.85 | K11: =I11*J11 -> 27047 | L11: 46283 | M11: =Settings!$B$3-DATE(2026,8,10) -> 38 | N11: 46232 | O11: yeongeun | P11: CPG | Q11: Korean Beauty | R11: amorepacific.com
A12: sparkli | B12: Sparkli Paid Ads Campaign | C12: Ritchie Boubouli | D12: Levi Hoang | E12: Existing client | F12: IO Sent Out | G12: 30000 | H12: USD | I12: =G12*INDEX(Settings!$B$6:$B$8,MATCH(H12,Settings!$A$6:$A$8,0)) -> 22200 | J12: =INDEX(Settings!$C$11:$C$16,MATCH(F12,Settings!$A$11:$A$16,0)) -> 0.85 | K12: =I12*J12 -> 18870 | L12: 46276 | M12: =Settings!$B$3-DATE(2026,9,15) -> 2 | N12: 46269 | O12: @sparkli.ai | P12: Tech | Q12: Kids EdTech App | R12: sparkli.ai
A13: TFIT | B13: TFIT - USA Nano activation 3 months | C13: Valeriia Mukhai | D13: - | E13: Existing client | F13: IO Sent Out | G13: 9000 | H13: USD | I13: =G13*INDEX(Settings!$B$6:$B$8,MATCH(H13,Settings!$A$6:$A$8,0)) -> 6660 | J13: =INDEX(Settings!$C$11:$C$16,MATCH(F13,Settings!$A$11:$A$16,0)) -> 0.85 | K13: =I13*J13 -> 5661 | L13: 46295 | M13: =Settings!$B$3-DATE(2026,9,15) -> 2 | N13: 46279 | O13: Elly | P13: CPG | Q13: Korean Beauty | R13: tfit.co.kr
A14: Zonevoice | B14: Twigo Launch SOW 1 - SEP 26 | C14: Carrick Klopper | D14: - | E14: New business | F14: Negotiation | G14: 150000 | H14: USD | I14: =G14*INDEX(Settings!$B$6:$B$8,MATCH(H14,Settings!$A$6:$A$8,0)) -> 111000 | J14: =INDEX(Settings!$C$11:$C$16,MATCH(F14,Settings!$A$11:$A$16,0)) -> 0.75 | K14: =I14*J14 -> 83250 | L14: 46326 | M14: =Settings!$B$3-DATE(2026,6,29) -> 80 | N14: 45903 | O14: Marc Tanas | P14: Travel & Telecom | Q14: eSIM App | R14: zonevoice.com
A15: sparkli | B15: Sparkli Influencer Marketing & UGC Content Campaign x Sept 2026 | C15: Ritchie Boubouli | D15: Levi Hoang | E15: Existing client | F15: Negotiation | G15: 75000 | H15: USD | I15: =G15*INDEX(Settings!$B$6:$B$8,MATCH(H15,Settings!$A$6:$A$8,0)) -> 55500 | J15: =INDEX(Settings!$C$11:$C$16,MATCH(F15,Settings!$A$11:$A$16,0)) -> 0.75 | K15: =I15*J15 -> 41625 | L15: 46276 | M15: =Settings!$B$3-DATE(2026,8,28) -> 20 | N15: 46250 | O15: @sparkli.ai | P15: Tech | Q15: Kids EdTech App | R15: sparkli.ai
A16: Sam'U | B16: Sam'U Black Friday Campaign | C16: Valeriia Mukhai | D16: Maggie Parrott | E16: Existing client | F16: Negotiation | G16: 70000 | H16: USD | I16: =G16*INDEX(Settings!$B$6:$B$8,MATCH(H16,Settings!$A$6:$A$8,0)) -> 51800 | J16: =INDEX(Settings!$C$11:$C$16,MATCH(F16,Settings!$A$11:$A$16,0)) -> 0.75 | K16: =I16*J16 -> 38850 | L16: 46283 | M16: =Settings!$B$3-DATE(2026,9,10) -> 7 | N16: 46269 | O16: jjk | P16: CPG | Q16: Korean Beauty | R16: samchic.co.kr
A17: Beauty of Joseon | B17: Beauty of Joseon - Germany / November | C17: Valeriia Mukhai | D17: Maggie Parrott | E17: Existing client | F17: Negotiation | G17: 60000 | H17: EUR | I17: =G17*INDEX(Settings!$B$6:$B$8,MATCH(H17,Settings!$A$6:$A$8,0)) -> 51000 | J17: =INDEX(Settings!$C$11:$C$16,MATCH(F17,Settings!$A$11:$A$16,0)) -> 0.75 | K17: =I17*J17 -> 38250 | L17: 46325 | M17: =Settings!$B$3-DATE(2026,9,10) -> 7 | N17: 46240 | O17: ezly | P17: CPG | Q17: Korean Beauty | R17: beautyofjoseon.com
A18: Comfort Click | B18: Comfort Click UK Celebrity SOW 3 - SEP 26 | C18: Carrick Klopper | D18: - | E18: Existing client | F18: Negotiation | G18: 50000 | H18: GBP | I18: =G18*INDEX(Settings!$B$6:$B$8,MATCH(H18,Settings!$A$6:$A$8,0)) -> 50000 | J18: =INDEX(Settings!$C$11:$C$16,MATCH(F18,Settings!$A$11:$A$16,0)) -> 0.75 | K18: =I18*J18 -> 37500 | L18: 46295 | M18: =Settings!$B$3-DATE(2026,8,31) -> 17 | N18: 46148 | O18: Prateek Tyagi | P18: Tech | Q18: Smart Home | R18: comfortclick.co.uk
A19: TeamSport | B19: TeamSport SOW 1 - SEP 26 | C19: Carrick Klopper | D19: - | E19: New business | F19: Negotiation | G19: 45000 | H19: GBP | I19: =G19*INDEX(Settings!$B$6:$B$8,MATCH(H19,Settings!$A$6:$A$8,0)) -> 45000 | J19: =INDEX(Settings!$C$11:$C$16,MATCH(F19,Settings!$A$11:$A$16,0)) -> 0.75 | K19: =I19*J19 -> 33750 | L19: 46295 | M19: =Settings!$B$3-DATE(2026,7,24) -> 55 | N19: 46203 | O19: Angela Porter | P19: Entertainment | Q19: Indoor Go-Karting | R19: team-sport.com
A20: FINOM | B20: FINOM - IO11 / Oct-Dec 2026 | C20: Valeriia Mukhai | D20: Emma-Leigh Pedder | E20: Existing client | F20: Negotiation | G20: 50000 | H20: EUR | I20: =G20*INDEX(Settings!$B$6:$B$8,MATCH(H20,Settings!$A$6:$A$8,0)) -> 42500 | J20: =INDEX(Settings!$C$11:$C$16,MATCH(F20,Settings!$A$11:$A$16,0)) -> 0.75 | K20: =I20*J20 -> 31875 | L20: 46325 | M20: =Settings!$B$3-DATE(2026,9,16) -> 1 | N20: 46252 | O20: Aglaya Dvornikova | P20: Finance | Q20: Fintech | R20: finom.co
A21: Beauty of Joseon | B21: Beauty of Joseon - Germany / November | C21: Valeriia Mukhai | D21: Maggie Parrott | E21: Existing client | F21: Negotiation | G21: 50000 | H21: EUR | I21: =G21*INDEX(Settings!$B$6:$B$8,MATCH(H21,Settings!$A$6:$A$8,0)) -> 42500 | J21: =INDEX(Settings!$C$11:$C$16,MATCH(F21,Settings!$A$11:$A$16,0)) -> 0.75 | K21: =I21*J21 -> 31875 | L21: 46325 | M21: =Settings!$B$3-DATE(2026,9,10) -> 7 | N21: 46252 | O21: ezly | P21: CPG | Q21: Korean Beauty | R21: beautyofjoseon.com
A22: Dumbbell's Incorporated | B22: Dumbbell's Incorporated SOW1 - SEP 26 | C22: Carrick Klopper | D22: - | E22: New business | F22: Negotiation | G22: 50000 | H22: USD | I22: =G22*INDEX(Settings!$B$6:$B$8,MATCH(H22,Settings!$A$6:$A$8,0)) -> 37000 | J22: =INDEX(Settings!$C$11:$C$16,MATCH(F22,Settings!$A$11:$A$16,0)) -> 0.75 | K22: =I22*J22 -> 27750 | L22: 46326 | M22: =Settings!$B$3-DATE(2026,9,7) -> 10 | N22: 45855 | O22: Bob Barreca
A23: I-World | B23: I-World - Brand 1 - 6 months USA | C23: Valeriia Mukhai | D23: - | E23: New business | F23: Negotiation | G23: 50000 | H23: USD | I23: =G23*INDEX(Settings!$B$6:$B$8,MATCH(H23,Settings!$A$6:$A$8,0)) -> 37000 | J23: =INDEX(Settings!$C$11:$C$16,MATCH(F23,Settings!$A$11:$A$16,0)) -> 0.75 | K23: =I23*J23 -> 27750 | L23: 46356 | M23: =Settings!$B$3-DATE(2026,9,15) -> 2 | N23: 46196 | O23: Daniel Yi | P23: CPG | Q23: Korean Beauty | R23: iworldus.com
A24: Oreate AI | B24: Oreate AI - US Q4 - SOW 3 - SEP 26 | C24: Carrick Klopper | D24: Lucia Lopez Moreno | E24: Existing client | F24: Negotiation | G24: 50000 | H24: USD | I24: =G24*INDEX(Settings!$B$6:$B$8,MATCH(H24,Settings!$A$6:$A$8,0)) -> 37000 | J24: =INDEX(Settings!$C$11:$C$16,MATCH(F24,Settings!$A$11:$A$16,0)) -> 0.75 | K24: =I24*J24 -> 27750 | L24: 46295 | M24: =Settings!$B$3-DATE(2026,8,12) -> 36 | N24: 46226 | O24: Raul Tang | P24: Tech | Q24: AI | R24: oreateai.com
A25: Vitrin Clinic | B25: Vitrin Clinic - SOW 1 - SEP 26 | C25: Carrick Klopper | D25: - | E25: New business | F25: Negotiation | G25: 50000 | H25: USD | I25: =G25*INDEX(Settings!$B$6:$B$8,MATCH(H25,Settings!$A$6:$A$8,0)) -> 37000 | J25: =INDEX(Settings!$C$11:$C$16,MATCH(F25,Settings!$A$11:$A$16,0)) -> 0.75 | K25: =I25*J25 -> 27750 | L25: 46295 | M25: =Settings!$B$3-DATE(2026,9,14) -> 3 | N25: 46279 | O25: Serdar Avşar | P25: Healthcare | Q25: Aesthetic Clinic | R25: vitrinclinic.com
A26: Vitrin Clinic | B26: Vitrin Clinic - SOW 2 - OCT 26 | C26: Carrick Klopper | D26: - | E26: New business | F26: Negotiation | G26: 50000 | H26: USD | I26: =G26*INDEX(Settings!$B$6:$B$8,MATCH(H26,Settings!$A$6:$A$8,0)) -> 37000 | J26: =INDEX(Settings!$C$11:$C$16,MATCH(F26,Settings!$A$11:$A$16,0)) -> 0.75 | K26: =I26*J26 -> 27750 | L26: 46326 | M26: =Settings!$B$3-DATE(2026,9,14) -> 3 | N26: 46279 | O26: Serdar Avşar | P26: Healthcare | Q26: Aesthetic Clinic | R26: vitrinclinic.com
A27: Firerock Capital | B27: Cinder & Crowns SOW 1 - SEP 26 | C27: Carrick Klopper | D27: - | E27: New business | F27: Negotiation | G27: 45000 | H27: USD | I27: =G27*INDEX(Settings!$B$6:$B$8,MATCH(H27,Settings!$A$6:$A$8,0)) -> 33300 | J27: =INDEX(Settings!$C$11:$C$16,MATCH(F27,Settings!$A$11:$A$16,0)) -> 0.75 | K27: =I27*J27 -> 24975 | L27: 46326 | M27: =Settings!$B$3-DATE(2026,8,24) -> 24 | N27: 46233 | O27: June Kwa | P27: Entertainment | Q27: Mobile Game | R27: firerock.sg
A28: Paddywax | B28: Paddywax x TikTok Shop SOW1 | C28: Valeriia Mukhai | D28: - | E28: New business | F28: Negotiation | G28: 40000 | H28: USD | I28: =G28*INDEX(Settings!$B$6:$B$8,MATCH(H28,Settings!$A$6:$A$8,0)) -> 29600 | J28: =INDEX(Settings!$C$11:$C$16,MATCH(F28,Settings!$A$11:$A$16,0)) -> 0.75 | K28: =I28*J28 -> 22200 | L28: 46295 | M28: =Settings!$B$3-DATE(2026,9,7) -> 10 | N28: 46191 | O28: Alexi Mintz | P28: CPG | Q28: Home Fragrance | R28: paddywax.com
A29: Astrotalk | B29: Astrotalk YT & IG SOW 3 - SEP 26 | C29: Carrick Klopper | D29: Lucia Lopez Moreno | E29: Existing client | F29: Negotiation | G29: 40000 | H29: USD | I29: =G29*INDEX(Settings!$B$6:$B$8,MATCH(H29,Settings!$A$6:$A$8,0)) -> 29600 | J29: =INDEX(Settings!$C$11:$C$16,MATCH(F29,Settings!$A$11:$A$16,0)) -> 0.75 | K29: =I29*J29 -> 22200 | L29: 46295 | M29: =Settings!$B$3-DATE(2026,8,28) -> 20 | N29: 46258 | O29: Ishita Saxena | P29: Tech | Q29: Astrology App | R29: astrotalk.com
A30: BiteLab | B30: BiteLab - LILYEVE - Affiliate | C30: Valeriia Mukhai | D30: Emma-Leigh Pedder | E30: Existing client | F30: Negotiation | G30: 36000 | H30: USD | I30: =G30*INDEX(Settings!$B$6:$B$8,MATCH(H30,Settings!$A$6:$A$8,0)) -> 26640 | J30: =INDEX(Settings!$C$11:$C$16,MATCH(F30,Settings!$A$11:$A$16,0)) -> 0.75 | K30: =I30*J30 -> 19980 | L30: 46295 | M30: =Settings!$B$3-DATE(2026,9,7) -> 10 | N30: 46210 | O30: gaby.ham | P30: CPG | Q30: Korean Beauty | R30: bitelab.co.kr
A31: Myntro | B31: Myntro SOW 1 - SEP 26 | C31: Carrick Klopper | D31: - | E31: New business | F31: Negotiation | G31: 30000 | H31: EUR | I31: =G31*INDEX(Settings!$B$6:$B$8,MATCH(H31,Settings!$A$6:$A$8,0)) -> 25500 | J31: =INDEX(Settings!$C$11:$C$16,MATCH(F31,Settings!$A$11:$A$16,0)) -> 0.75 | K31: =I31*J31 -> 19125 | L31: 46295 | M31: =Settings!$B$3-DATE(2026,7,21) -> 58 | N31: 46146 | O31: Moa Tyborn | P31: Finance | Q31: Debt Management | R31: myntro.com
A32: BNC Korea | B32: BNC Korea Top Tier - SOW 2 - AUG 26 | C32: Carrick Klopper | D32: Blake Hoang | E32: Existing client | F32: Negotiation | G32: 30000 | H32: USD | I32: =G32*INDEX(Settings!$B$6:$B$8,MATCH(H32,Settings!$A$6:$A$8,0)) -> 22200 | J32: =INDEX(Settings!$C$11:$C$16,MATCH(F32,Settings!$A$11:$A$16,0)) -> 0.75 | K32: =I32*J32 -> 16650 | L32: 46356 | M32: =Settings!$B$3-DATE(2026,6,24) -> 85 | N32: 46197 | O32: hihong | P32: Healthcare | Q32: Biopharma / Aesthetics | R32: bnckorea.co.kr
A33: Astrotalk | B33: Astrotalk UGC SOW 4 - SEP 26 | C33: Carrick Klopper | D33: Lucia Lopez Moreno | E33: Existing client | F33: Negotiation | G33: 30000 | H33: USD | I33: =G33*INDEX(Settings!$B$6:$B$8,MATCH(H33,Settings!$A$6:$A$8,0)) -> 22200 | J33: =INDEX(Settings!$C$11:$C$16,MATCH(F33,Settings!$A$11:$A$16,0)) -> 0.75 | K33: =I33*J33 -> 16650 | L33: 46286 | M33: =Settings!$B$3-DATE(2026,9,7) -> 10 | N33: 46272 | O33: Ishita Saxena | P33: Tech | Q33: Astrology App | R33: astrotalk.com
A34: TFIT | B34: TFIT / Czech Black Friday / Rossmann | C34: Valeriia Mukhai | D34: - | E34: Existing client | F34: Negotiation | G34: 30000 | H34: USD | I34: =G34*INDEX(Settings!$B$6:$B$8,MATCH(H34,Settings!$A$6:$A$8,0)) -> 22200 | J34: =INDEX(Settings!$C$11:$C$16,MATCH(F34,Settings!$A$11:$A$16,0)) -> 0.75 | K34: =I34*J34 -> 16650 | L34: 46295 | M34: =Settings!$B$3-DATE(2026,9,10) -> 7 | N34: 46275 | O34: Elly | P34: CPG | Q34: Korean Beauty | R34: tfit.co.kr
A35: Beauty of Joseon | B35: Germany Tinted Sunscreen SPF | C35: Valeriia Mukhai | D35: Maggie Parrott | E35: Existing client | F35: Negotiation | G35: 20000 | H35: EUR | I35: =G35*INDEX(Settings!$B$6:$B$8,MATCH(H35,Settings!$A$6:$A$8,0)) -> 17000 | J35: =INDEX(Settings!$C$11:$C$16,MATCH(F35,Settings!$A$11:$A$16,0)) -> 0.75 | K35: =I35*J35 -> 12750 | M35: =Settings!$B$3-DATE(2026,9,10) -> 7 | N35: 46273 | O35: ezly | P35: CPG | Q35: Korean Beauty | R35: beautyofjoseon.com
A36: Scrub Daddy | B36: Scrub Daddy Influencer Campaign x Germany & Spain | C36: Ritchie Boubouli | D36: Sarineh Garapetian | E36: Existing client | F36: Negotiation | G36: 15000 | H36: GBP | I36: =G36*INDEX(Settings!$B$6:$B$8,MATCH(H36,Settings!$A$6:$A$8,0)) -> 15000 | J36: =INDEX(Settings!$C$11:$C$16,MATCH(F36,Settings!$A$11:$A$16,0)) -> 0.75 | K36: =I36*J36 -> 11250 | L36: 46290 | M36: =Settings!$B$3-DATE(2026,7,9) -> 70 | N36: 46148 | O36: Sylvia Jacob | P36: CPG | Q36: Household Cleaning | R36: scrubdaddy.eu
A37: Webull Securities | B37: Webull Securities x Influencer Campaign Part 2 | C37: Ritchie Boubouli | D37: Levi Hoang | E37: Existing client | F37: Feedback | G37: 250000 | H37: GBP | I37: =G37*INDEX(Settings!$B$6:$B$8,MATCH(H37,Settings!$A$6:$A$8,0)) -> 250000 | J37: =INDEX(Settings!$C$11:$C$16,MATCH(F37,Settings!$A$11:$A$16,0)) -> 0.6 | K37: =I37*J37 -> 150000 | L37: 46312 | M37: =Settings!$B$3-DATE(2026,8,19) -> 29 | N37: 46253 | O37: Nick Saunders | P37: Finance | Q37: Online Trading | R37: webull-uk.com
A38: Beauty of Joseon | B38: Beauty of Joseon - Another one - September | C38: Valeriia Mukhai | D38: Maggie Parrott | E38: Existing client | F38: Feedback | G38: 150000 | H38: GBP | I38: =G38*INDEX(Settings!$B$6:$B$8,MATCH(H38,Settings!$A$6:$A$8,0)) -> 150000 | J38: =INDEX(Settings!$C$11:$C$16,MATCH(F38,Settings!$A$11:$A$16,0)) -> 0.6 | K38: =I38*J38 -> 90000 | L38: 46280 | M38: =Settings!$B$3-DATE(2026,8,31) -> 17 | N38: 46177 | O38: haram | P38: CPG | Q38: Korean Beauty | R38: beautyofjoseon.com
A39: Art Gallery of Ontario | B39: Art Gallery of Ontario SOW 1 - MAR 27 | C39: Carrick Klopper | D39: - | E39: New business | F39: Feedback | G39: 140000 | H39: USD | I39: =G39*INDEX(Settings!$B$6:$B$8,MATCH(H39,Settings!$A$6:$A$8,0)) -> 103600 | J39: =INDEX(Settings!$C$11:$C$16,MATCH(F39,Settings!$A$11:$A$16,0)) -> 0.6 | K39: =I39*J39 -> 62160 | L39: 46356 | M39: =Settings!$B$3-DATE(2026,8,5) -> 43 | N39: 46216 | O39: Ros Lawler | P39: Entertainment | Q39: Art Gallery | R39: ago.ca
A40: Darts Corner | B40: Mission Darts - FY 27 - SOW 1 - NOV 26 | C40: Carrick Klopper | D40: - | E40: New business | F40: Feedback | G40: 100000 | H40: GBP | I40: =G40*INDEX(Settings!$B$6:$B$8,MATCH(H40,Settings!$A$6:$A$8,0)) -> 100000 | J40: =INDEX(Settings!$C$11:$C$16,MATCH(F40,Settings!$A$11:$A$16,0)) -> 0.6 | K40: =I40*J40 -> 60000 | L40: 46356 | M40: =Settings!$B$3-DATE(2026,2,5) -> 224 | N40: 46052 | O40: Craig Heenighan | P40: Retail | Q40: Darts Equipment | R40: dartscorner.co.uk
A41: EFG International | B41: EFG International SOW 1 - SEP 26 | C41: Carrick Klopper | D41: - | E41: New business | F41: Feedback | G41: 90000 | H41: GBP | I41: =G41*INDEX(Settings!$B$6:$B$8,MATCH(H41,Settings!$A$6:$A$8,0)) -> 90000 | J41: =INDEX(Settings!$C$11:$C$16,MATCH(F41,Settings!$A$11:$A$16,0)) -> 0.6 | K41: =I41*J41 -> 54000 | L41: 46326 | M41: =Settings!$B$3-DATE(2026,9,17) -> 0 | N41: 46272 | O41: Neil Thornburn | P41: Finance | Q41: Private Banking | R41: efginternational.com
A42: Kedrion Biopharma | B42: Kedrion SOW 1 FY 27 - OCT 26 | C42: Carrick Klopper | D42: - | E42: New business | F42: Feedback | G42: 90000 | H42: EUR | I42: =G42*INDEX(Settings!$B$6:$B$8,MATCH(H42,Settings!$A$6:$A$8,0)) -> 76500 | J42: =INDEX(Settings!$C$11:$C$16,MATCH(F42,Settings!$A$11:$A$16,0)) -> 0.6 | K42: =I42*J42 -> 45900 | L42: 46295 | M42: =Settings!$B$3-DATE(2026,3,19) -> 182 | N42: 45973 | O42: Duccio Manetti | P42: Healthcare | Q42: Biopharma | R42: kedrion.com
A43: Beauty of Joseon | B43: Beauty of Joseon - UK Campaign / October | C43: Valeriia Mukhai | D43: Maggie Parrott | E43: Existing client | F43: Feedback | G43: 75000 | H43: GBP | I43: =G43*INDEX(Settings!$B$6:$B$8,MATCH(H43,Settings!$A$6:$A$8,0)) -> 75000 | J43: =INDEX(Settings!$C$11:$C$16,MATCH(F43,Settings!$A$11:$A$16,0)) -> 0.6 | K43: =I43*J43 -> 45000 | L43: 46325 | M43: =Settings!$B$3-DATE(2026,9,10) -> 7 | N43: 46252 | O43: haram | P43: CPG | Q43: Korean Beauty | R43: beautyofjoseon.com
A44: Beauty of Joseon | B44: Beauty of Joseon - UK Campaign / November | C44: Valeriia Mukhai | D44: Maggie Parrott | E44: Existing client | F44: Feedback | G44: 75000 | H44: GBP | I44: =G44*INDEX(Settings!$B$6:$B$8,MATCH(H44,Settings!$A$6:$A$8,0)) -> 75000 | J44: =INDEX(Settings!$C$11:$C$16,MATCH(F44,Settings!$A$11:$A$16,0)) -> 0.6 | K44: =I44*J44 -> 45000 | L44: 46325 | M44: =Settings!$B$3-DATE(2026,9,10) -> 7 | N44: 46252 | O44: haram | P44: CPG | Q44: Korean Beauty | R44: beautyofjoseon.com
A45: Ramsey's Solutions | B45: Ramsey's Solutions SOW 1 - APR 26 | C45: Carrick Klopper | D45: - | E45: New business | F45: Feedback | G45: 100000 | H45: USD | I45: =G45*INDEX(Settings!$B$6:$B$8,MATCH(H45,Settings!$A$6:$A$8,0)) -> 74000 | J45: =INDEX(Settings!$C$11:$C$16,MATCH(F45,Settings!$A$11:$A$16,0)) -> 0.6 | K45: =I45*J45 -> 44400 | L45: 46325 | M45: =Settings!$B$3-DATE(2025,12,11) -> 280 | N45: 45996 | O45: Kimbrelly Kegler | P45: Finance | Q45: Personal Finance Education | R45: ramseysolutions.com
A46: Ollies Bargain Outlets | B46: Ollies Bargain Outlets | C46: Ritchie Boubouli | D46: - | E46: New business | F46: Feedback | G46: 100000 | H46: USD | I46: =G46*INDEX(Settings!$B$6:$B$8,MATCH(H46,Settings!$A$6:$A$8,0)) -> 74000 | J46: =INDEX(Settings!$C$11:$C$16,MATCH(F46,Settings!$A$11:$A$16,0)) -> 0.6 | K46: =I46*J46 -> 44400 | L46: 46276 | M46: =Settings!$B$3-DATE(2026,6,10) -> 99 | N46: 46128 | O46: josipa Topic | P46: Retail | Q46: Discount Retail | R46: ollies.us
A47: Verizon | B47: Verizon - Gizmo Watch - SOW1 - SEP 26 | C47: Carrick Klopper | D47: - | E47: New business | F47: Feedback | G47: 100000 | H47: USD | I47: =G47*INDEX(Settings!$B$6:$B$8,MATCH(H47,Settings!$A$6:$A$8,0)) -> 74000 | J47: =INDEX(Settings!$C$11:$C$16,MATCH(F47,Settings!$A$11:$A$16,0)) -> 0.6 | K47: =I47*J47 -> 44400 | L47: 46295 | M47: =Settings!$B$3-DATE(2026,8,28) -> 20 | N47: 46174 | O47: Brian Suchak | P47: Travel & Telecom | Q47: Telecom | R47: verizon.com
A48: GLŌLABZ | B48: GLŌLABZ x TikTok Marketing Campaign | C48: Ritchie Boubouli | D48: - | E48: New business | F48: Feedback | G48: 100000 | H48: USD | I48: =G48*INDEX(Settings!$B$6:$B$8,MATCH(H48,Settings!$A$6:$A$8,0)) -> 74000 | J48: =INDEX(Settings!$C$11:$C$16,MATCH(F48,Settings!$A$11:$A$16,0)) -> 0.6 | K48: =I48*J48 -> 44400 | L48: 46339 | M48: =Settings!$B$3-DATE(2026,8,16) -> 32 | N48: 46213 | O48: Sonny Freeman | P48: CPG | Q48: Beauty | R48: glolabz.com
A49: merakitech | B49: Meraki [Influencer + KOL] - Monthly | C49: Ritchie Boubouli | D49: Levi Hoang | E49: Existing client | F49: Feedback | G49: 100000 | H49: USD | I49: =G49*INDEX(Settings!$B$6:$B$8,MATCH(H49,Settings!$A$6:$A$8,0)) -> 74000 | J49: =INDEX(Settings!$C$11:$C$16,MATCH(F49,Settings!$A$11:$A$16,0)) -> 0.6 | K49: =I49*J49 -> 44400 | M49: =Settings!$B$3-DATE(2026,9,2) -> 15 | N49: 46267 | O49: Tracy Cai | P49: Tech | Q49: SaaS | R49: merakitech.com
A50: Galderma | B50: Cetaphil Romania | C50: Ritchie Boubouli | D50: Sarineh Garapetian | E50: Existing client | F50: Feedback | G50: 80000 | H50: EUR | I50: =G50*INDEX(Settings!$B$6:$B$8,MATCH(H50,Settings!$A$6:$A$8,0)) -> 68000 | J50: =INDEX(Settings!$C$11:$C$16,MATCH(F50,Settings!$A$11:$A$16,0)) -> 0.6 | K50: =I50*J50 -> 40800 | L50: 46295 | M50: =Settings!$B$3-DATE(2026,3,18) -> 183 | N50: 46000 | O50: monika lamparska kania | P50: Healthcare | Q50: Dermatology / Pharma | R50: galderma.com
A51: Monogram AI, Inc. | B51: Monogram AI SOW 1 - AUG 26 | C51: Carrick Klopper | D51: - | E51: New business | F51: Feedback | G51: 90000 | H51: USD | I51: =G51*INDEX(Settings!$B$6:$B$8,MATCH(H51,Settings!$A$6:$A$8,0)) -> 66600 | J51: =INDEX(Settings!$C$11:$C$16,MATCH(F51,Settings!$A$11:$A$16,0)) -> 0.6 | K51: =I51*J51 -> 39960 | L51: 46295 | M51: =Settings!$B$3-DATE(2026,9,14) -> 3 | N51: 46253 | O51: EREN BALI | P51: Tech | Q51: AI Consumer App | R51: monogram.ai
A52: Neals Yard Remedies | B52: Neals Yard Remedies x TikTok Campaign | C52: Ritchie Boubouli | D52: - | E52: Existing client | F52: Feedback | G52: 60000 | H52: GBP | I52: =G52*INDEX(Settings!$B$6:$B$8,MATCH(H52,Settings!$A$6:$A$8,0)) -> 60000 | J52: =INDEX(Settings!$C$11:$C$16,MATCH(F52,Settings!$A$11:$A$16,0)) -> 0.6 | K52: =I52*J52 -> 36000 | L52: 46295 | M52: =Settings!$B$3-DATE(2026,8,28) -> 20 | N52: 46148 | O52: Goh | P52: CPG | Q52: Beauty | R52: nealsyardremedies.com
A53: Viora | B53: Viora x Influencer Marketing, UGC, Paid Ads Campaign | C53: Ritchie Boubouli | D53: Lucia Lopez Moreno | E53: Existing client | F53: Feedback | G53: 60000 | H53: USD | I53: =G53*INDEX(Settings!$B$6:$B$8,MATCH(H53,Settings!$A$6:$A$8,0)) -> 44400 | J53: =INDEX(Settings!$C$11:$C$16,MATCH(F53,Settings!$A$11:$A$16,0)) -> 0.6 | K53: =I53*J53 -> 26640 | L53: 46295 | M53: =Settings!$B$3-DATE(2026,9,7) -> 10 | N53: 46262 | O53: Michael McDade | P53: Healthcare | Q53: FemTech Diagnostics | R53: vioratest.com
A54: Amplify Ventures Ltd. | B54: Amplify Ventures eSIM SOW 1 - SEP 26 | C54: Carrick Klopper | D54: - | E54: New business | F54: Feedback | G54: 60000 | H54: USD | I54: =G54*INDEX(Settings!$B$6:$B$8,MATCH(H54,Settings!$A$6:$A$8,0)) -> 44400 | J54: =INDEX(Settings!$C$11:$C$16,MATCH(F54,Settings!$A$11:$A$16,0)) -> 0.6 | K54: =I54*J54 -> 26640 | L54: 46295 | M54: =Settings!$B$3-DATE(2026,9,11) -> 6 | N54: 46276 | O54: Ishita Chaudhary | P54: Travel & Telecom | Q54: eSIM App | R54: studiomosaicapps.com
A55: THE RIVIERA | B55: RIVIERA - SOW1 | C55: Valeriia Mukhai | D55: - | E55: New business | F55: Feedback | G55: 50000 | H55: USD | I55: =G55*INDEX(Settings!$B$6:$B$8,MATCH(H55,Settings!$A$6:$A$8,0)) -> 37000 | J55: =INDEX(Settings!$C$11:$C$16,MATCH(F55,Settings!$A$11:$A$16,0)) -> 0.6 | K55: =I55*J55 -> 22200 | L55: 46324 | M55: =Settings!$B$3-DATE(2026,8,13) -> 35 | N55: 46049 | O55: Heejae Choi | P55: CPG | Q55: Fragrance Mists | R55: riviera-dazur.com
A56: Mars Royal Canin | B56: Royal Canin Argentina | C56: Ritchie Boubouli | D56: Lucia Lopez Moreno | E56: Existing client | F56: Feedback | G56: 50000 | H56: USD | I56: =G56*INDEX(Settings!$B$6:$B$8,MATCH(H56,Settings!$A$6:$A$8,0)) -> 37000 | J56: =INDEX(Settings!$C$11:$C$16,MATCH(F56,Settings!$A$11:$A$16,0)) -> 0.6 | K56: =I56*J56 -> 22200 | L56: 46295 | M56: =Settings!$B$3-DATE(2026,6,10) -> 99 | N56: 46128 | O56: riccarda Schmidt | P56: CPG | Q56: Pet Food | R56: royalcanin.com
A57: Aldermore | B57: Aldermore SOW 1 - OCT 26 | C57: Carrick Klopper | D57: - | E57: New business | F57: Feedback | G57: 25000 | H57: GBP | I57: =G57*INDEX(Settings!$B$6:$B$8,MATCH(H57,Settings!$A$6:$A$8,0)) -> 25000 | J57: =INDEX(Settings!$C$11:$C$16,MATCH(F57,Settings!$A$11:$A$16,0)) -> 0.6 | K57: =I57*J57 -> 15000 | L57: 46326 | M57: =Settings!$B$3-DATE(2026,9,8) -> 9 | N57: 46100 | O57: David Reynell | P57: Finance | Q57: Bank | R57: aldermore.co.uk
A58: Pacsen | B58: Pacsen - DrSavers | C58: Valeriia Mukhai | D58: - | E58: New business | F58: Feedback | G58: 30000 | H58: USD | I58: =G58*INDEX(Settings!$B$6:$B$8,MATCH(H58,Settings!$A$6:$A$8,0)) -> 22200 | J58: =INDEX(Settings!$C$11:$C$16,MATCH(F58,Settings!$A$11:$A$16,0)) -> 0.6 | K58: =I58*J58 -> 13320 | L58: 46325 | M58: =Settings!$B$3-DATE(2026,9,7) -> 10 | N58: 46153 | O58: jason.suk | P58: Retail | Q58: Sporting Goods OEM | R58: pacsen.net
A59: CornBreadHemp | B59: CornBreadHemp / Pilot | C59: Valeriia Mukhai | D59: - | E59: New business | F59: Feedback | G59: 30000 | H59: USD | I59: =G59*INDEX(Settings!$B$6:$B$8,MATCH(H59,Settings!$A$6:$A$8,0)) -> 22200 | J59: =INDEX(Settings!$C$11:$C$16,MATCH(F59,Settings!$A$11:$A$16,0)) -> 0.6 | K59: =I59*J59 -> 13320 | L59: 46295 | M59: =Settings!$B$3-DATE(2026,9,15) -> 2 | N59: 46253 | O59: kelli | P59: Health & Wellness | Q59: CBD | R59: cornbreadhemp.com
A60: Wednesday Waffles | B60: Wednesday Waffles SOW 1 - SEP 26 | C60: Carrick Klopper | D60: - | E60: New business | F60: Feedback | G60: 30000 | H60: USD | I60: =G60*INDEX(Settings!$B$6:$B$8,MATCH(H60,Settings!$A$6:$A$8,0)) -> 22200 | J60: =INDEX(Settings!$C$11:$C$16,MATCH(F60,Settings!$A$11:$A$16,0)) -> 0.6 | K60: =I60*J60 -> 13320 | L60: 46295 | M60: =Settings!$B$3-DATE(2026,9,17) -> 0 | N60: 46279 | O60: Zameer Masjedee | P60: Tech | Q60: Social Video App | R60: wednesdaywaffles.com
A61: Birmingham City FC | B61: Birmingham City FC SOW 1 - AUG 26 | C61: Carrick Klopper | D61: - | E61: New business | F61: Feedback | G61: 20000 | H61: GBP | I61: =G61*INDEX(Settings!$B$6:$B$8,MATCH(H61,Settings!$A$6:$A$8,0)) -> 20000 | J61: =INDEX(Settings!$C$11:$C$16,MATCH(F61,Settings!$A$11:$A$16,0)) -> 0.6 | K61: =I61*J61 -> 12000 | L61: 46295 | M61: =Settings!$B$3-DATE(2026,5,22) -> 118 | N61: 46148 | O61: Will Radford | P61: Entertainment | Q61: Football Club | R61: bcfc.com
A62: FINOM | B62: FINOM Event Budget OCT | C62: Valeriia Mukhai | D62: Emma-Leigh Pedder | E62: Existing client | F62: Feedback | G62: 20000 | H62: GBP | I62: =G62*INDEX(Settings!$B$6:$B$8,MATCH(H62,Settings!$A$6:$A$8,0)) -> 20000 | J62: =INDEX(Settings!$C$11:$C$16,MATCH(F62,Settings!$A$11:$A$16,0)) -> 0.6 | K62: =I62*J62 -> 12000 | L62: 46283 | M62: =Settings!$B$3-DATE(2026,9,16) -> 1 | N62: 46276 | O62: Aglaya Dvornikova | P62: Finance | Q62: Fintech | R62: finom.co
A63: Cosrx.co | B63: Affiliate Proposal COSRX US/EU | C63: Valeriia Mukhai | D63: Emma-Leigh Pedder | E63: Existing client | F63: Feedback | G63: 20000 | H63: USD | I63: =G63*INDEX(Settings!$B$6:$B$8,MATCH(H63,Settings!$A$6:$A$8,0)) -> 14800 | J63: =INDEX(Settings!$C$11:$C$16,MATCH(F63,Settings!$A$11:$A$16,0)) -> 0.6 | K63: =I63*J63 -> 8880 | L63: 46295 | M63: =Settings!$B$3-DATE(2026,9,16) -> 1 | N63: 46275 | O63: 정다운 | P63: CPG | Q63: Korean Beauty | R63: cosrx.com
A64: Isehan.co | B64: Isehan - UK activation | C64: Valeriia Mukhai | D64: Maggie Parrott | E64: Existing client | F64: Feedback | G64: 10000 | H64: GBP | I64: =G64*INDEX(Settings!$B$6:$B$8,MATCH(H64,Settings!$A$6:$A$8,0)) -> 10000 | J64: =INDEX(Settings!$C$11:$C$16,MATCH(F64,Settings!$A$11:$A$16,0)) -> 0.6 | K64: =I64*J64 -> 6000 | M64: =Settings!$B$3-DATE(2026,9,10) -> 7 | N64: 46269 | O64: Matsumoto_m | P64: CPG | Q64: Japanese Beauty | R64: isehan.co.jp
A65: Mars Royal Canin | B65: Royal Canin Influencer Campaign | C65: Ritchie Boubouli | D65: Lucia Lopez Moreno | E65: Existing client | F65: Present Proposal | G65: 250000 | H65: GBP | I65: =G65*INDEX(Settings!$B$6:$B$8,MATCH(H65,Settings!$A$6:$A$8,0)) -> 250000 | J65: =INDEX(Settings!$C$11:$C$16,MATCH(F65,Settings!$A$11:$A$16,0)) -> 0.55 | K65: =I65*J65 -> 137500 | L65: 46300 | M65: =Settings!$B$3-DATE(2026,6,22) -> 87 | N65: 46083 | O65: riccarda Schmidt | P65: CPG | Q65: Pet Food | R65: royalcanin.com
A66: Amorepacific | B66: Amorepacific - AESTURA | C66: Valeriia Mukhai | D66: Maggie Parrott | E66: Existing client | F66: Present Proposal | G66: 303500 | H66: USD | I66: =G66*INDEX(Settings!$B$6:$B$8,MATCH(H66,Settings!$A$6:$A$8,0)) -> 224590 | J66: =INDEX(Settings!$C$11:$C$16,MATCH(F66,Settings!$A$11:$A$16,0)) -> 0.55 | K66: =I66*J66 -> 123524.5 | L66: 46356 | M66: =Settings!$B$3-DATE(2026,9,14) -> 3 | N66: 46100 | O66: Judy - Jukyung Lee | P66: CPG | Q66: Korean Beauty | R66: amorepacific.com
A67: stellaris Robotics | B67: stellaris Robotics | C67: Ritchie Boubouli | D67: - | E67: New business | F67: Present Proposal | G67: 100000 | H67: GBP | I67: =G67*INDEX(Settings!$B$6:$B$8,MATCH(H67,Settings!$A$6:$A$8,0)) -> 100000 | J67: =INDEX(Settings!$C$11:$C$16,MATCH(F67,Settings!$A$11:$A$16,0)) -> 0.55 | K67: =I67*J67 -> 55000 | L67: 46290 | M67: =Settings!$B$3-DATE(2026,8,16) -> 32 | N67: 46250 | O67: Joe | P67: Tech | Q67: Consumer Robotics | R67: stellarisrobot.com
A68: Byoma | B68: Byoma x UGC Gifted Campaign | C68: Ritchie Boubouli | D68: Lucia Lopez Moreno | E68: Existing client | F68: Present Proposal | G68: 100000 | H68: USD | I68: =G68*INDEX(Settings!$B$6:$B$8,MATCH(H68,Settings!$A$6:$A$8,0)) -> 74000 | J68: =INDEX(Settings!$C$11:$C$16,MATCH(F68,Settings!$A$11:$A$16,0)) -> 0.55 | K68: =I68*J68 -> 40700 | L68: 46295 | M68: =Settings!$B$3-DATE(2026,8,17) -> 31 | N68: 46051 | O68: Tara Loftis | P68: CPG | Q68: Skincare | R68: byoma.com
A69: Quadthera | B69: Quadthera H2 - SOW 2 - AUG 26 | C69: Carrick Klopper | D69: - | E69: Existing client | F69: Present Proposal | G69: 100000 | H69: USD | I69: =G69*INDEX(Settings!$B$6:$B$8,MATCH(H69,Settings!$A$6:$A$8,0)) -> 74000 | J69: =INDEX(Settings!$C$11:$C$16,MATCH(F69,Settings!$A$11:$A$16,0)) -> 0.55 | K69: =I69*J69 -> 40700 | L69: 46295 | M69: =Settings!$B$3-DATE(2026,8,18) -> 30 | N69: 46226 | O69: Andrew Park | P69: Healthcare | Q69: Biotech
A70: Beauty of Joseon | B70: Beauty of Joseon - US Campaign | C70: Valeriia Mukhai | D70: Maggie Parrott | E70: Existing client | F70: Present Proposal | G70: 100000 | H70: USD | I70: =G70*INDEX(Settings!$B$6:$B$8,MATCH(H70,Settings!$A$6:$A$8,0)) -> 74000 | J70: =INDEX(Settings!$C$11:$C$16,MATCH(F70,Settings!$A$11:$A$16,0)) -> 0.55 | K70: =I70*J70 -> 40700 | L70: 46325 | M70: =Settings!$B$3-DATE(2026,9,11) -> 6 | N70: 46276 | O70: haram | P70: CPG | Q70: Korean Beauty | R70: beautyofjoseon.com
A71: Skylum | B71: Skylum - SOW2 / Creator programme 3-month test (Luminar) | C71: Valeriia Mukhai | D71: - | E71: Existing client | F71: Present Proposal | G71: 60000 | H71: USD | I71: =G71*INDEX(Settings!$B$6:$B$8,MATCH(H71,Settings!$A$6:$A$8,0)) -> 44400 | J71: =INDEX(Settings!$C$11:$C$16,MATCH(F71,Settings!$A$11:$A$16,0)) -> 0.55 | K71: =I71*J71 -> 24420 | L71: 46295 | M71: =Settings!$B$3-DATE(2026,9,17) -> 0 | N71: 46282 | O71: Kateryna Medushyvska | P71: Tech | Q71: Creative SaaS | R71: skylum.com
A72: Opera Browser | B72: Opera - SOW38 / Always On Sept-Oct | C72: Valeriia Mukhai | D72: Emma-Leigh Pedder | E72: Existing client | F72: Present Proposal | G72: 50000 | H72: USD | I72: =G72*INDEX(Settings!$B$6:$B$8,MATCH(H72,Settings!$A$6:$A$8,0)) -> 37000 | J72: =INDEX(Settings!$C$11:$C$16,MATCH(F72,Settings!$A$11:$A$16,0)) -> 0.55 | K72: =I72*J72 -> 20350 | L72: 46290 | M72: =Settings!$B$3-DATE(2026,8,31) -> 17 | N72: 46252 | O72: Shallana Santos | P72: Tech | Q72: SaaS | R72: opera.com
A73: mary browns | B73: Mary Browns - Influencer Campaign [Launch] | C73: Ritchie Boubouli | D73: Levi Hoang | E73: Existing client | F73: Present Proposal | G73: 50000 | H73: USD | I73: =G73*INDEX(Settings!$B$6:$B$8,MATCH(H73,Settings!$A$6:$A$8,0)) -> 37000 | J73: =INDEX(Settings!$C$11:$C$16,MATCH(F73,Settings!$A$11:$A$16,0)) -> 0.55 | K73: =I73*J73 -> 20350 | M73: =Settings!$B$3-DATE(2026,9,7) -> 10 | N73: 46267 | O73: michelle payot | P73: Food & Beverage | Q73: QSR / Fast Food | R73: mbchicken.co.uk
A74: I-ne Co., Ltd. | B74: YOLU - I-ne SOW1 | C74: Valeriia Mukhai | D74: - | E74: New business | F74: Present Proposal | G74: 50000 | H74: USD | I74: =G74*INDEX(Settings!$B$6:$B$8,MATCH(H74,Settings!$A$6:$A$8,0)) -> 37000 | J74: =INDEX(Settings!$C$11:$C$16,MATCH(F74,Settings!$A$11:$A$16,0)) -> 0.55 | K74: =I74*J74 -> 20350 | L74: 46356 | M74: =Settings!$B$3-DATE(2026,9,15) -> 2 | N74: 46274 | O74: Lilia Yamakawa | P74: CPG | Q74: Japanese Beauty / Haircare | R74: i-ne.co.jp
A75: Vancouver Whitecaps FC | B75: Vancouver Whitecaps FC SOW 1 - OCT 26 | C75: Carrick Klopper | D75: - | E75: New business | F75: Present Proposal | G75: 40000 | H75: USD | I75: =G75*INDEX(Settings!$B$6:$B$8,MATCH(H75,Settings!$A$6:$A$8,0)) -> 29600 | J75: =INDEX(Settings!$C$11:$C$16,MATCH(F75,Settings!$A$11:$A$16,0)) -> 0.55 | K75: =I75*J75 -> 16280 | L75: 46326 | M75: =Settings!$B$3-DATE(2026,8,18) -> 30 | N75: 46246 | O75: Adam Ferreira | P75: Entertainment | Q75: Football Club | R75: whitecapsfc.com
A76: Expedia | B76: Expedia - RFP Participation | C76: Valeriia Mukhai | D76: - | E76: New business | F76: Present Proposal | G76: 10000 | H76: GBP | I76: =G76*INDEX(Settings!$B$6:$B$8,MATCH(H76,Settings!$A$6:$A$8,0)) -> 10000 | J76: =INDEX(Settings!$C$11:$C$16,MATCH(F76,Settings!$A$11:$A$16,0)) -> 0.55 | K76: =I76*J76 -> 5500 | L76: 46386 | M76: =Settings!$B$3-DATE(2026,9,17) -> 0 | N76: 46274 | O76: Stephanie Palos | P76: Travel & Telecom | Q76: OTA / Travel Platform | R76: expediagroup.com
A77: Kia | B77: KIA HQ - Creator Crew 2027 / Global (15 markets) | C77: Valeriia Mukhai | D77: - | E77: New business | F77: Create Proposal | G77: 1000000 | H77: USD | I77: =G77*INDEX(Settings!$B$6:$B$8,MATCH(H77,Settings!$A$6:$A$8,0)) -> 740000 | J77: =INDEX(Settings!$C$11:$C$16,MATCH(F77,Settings!$A$11:$A$16,0)) -> 0.5 | K77: =I77*J77 -> 370000 | L77: 46371 | M77: =Settings!$B$3-DATE(2026,9,8) -> 9 | N77: 46273 | O77: Ahreum Jang | P77: Automotive | Q77: Car Manufacturer | R77: kia.com
A78: Konu Food Corp | B78: Konu Snacks x TikTok Campaign x Sept 2026 | C78: Ritchie Boubouli | D78: Lucia Lopez Moreno | E78: Existing client | F78: Create Proposal | G78: 200000 | H78: USD | I78: =G78*INDEX(Settings!$B$6:$B$8,MATCH(H78,Settings!$A$6:$A$8,0)) -> 148000 | J78: =INDEX(Settings!$C$11:$C$16,MATCH(F78,Settings!$A$11:$A$16,0)) -> 0.5 | K78: =I78*J78 -> 74000 | L78: 46297 | M78: =Settings!$B$3-DATE(2026,9,3) -> 14 | N78: 46268 | O78: Patrick Paraguya | P78: Food & Beverage | Q78: Snacks | R78: konufoods.com
A79: Macaly | B79: Macaly - UGC + Influencer Europe Test (UK/DE/FR/ES/IT) / Q4 2026 | C79: Valeriia Mukhai | D79: - | E79: New business | F79: Create Proposal | G79: 100000 | H79: EUR | I79: =G79*INDEX(Settings!$B$6:$B$8,MATCH(H79,Settings!$A$6:$A$8,0)) -> 85000 | J79: =INDEX(Settings!$C$11:$C$16,MATCH(F79,Settings!$A$11:$A$16,0)) -> 0.5 | K79: =I79*J79 -> 42500 | L79: 46295 | M79: =Settings!$B$3-DATE(2026,9,17) -> 0 | N79: 46282 | O79: Juraj Mihalik | P79: Tech | Q79: AI Website Builder | R79: macaly.com
A80: Damm1876 | B80: Damm1876 - SOW 1 - OCT 26 | C80: Carrick Klopper | D80: - | E80: New business | F80: Create Proposal | G80: 50000 | H80: GBP | I80: =G80*INDEX(Settings!$B$6:$B$8,MATCH(H80,Settings!$A$6:$A$8,0)) -> 50000 | J80: =INDEX(Settings!$C$11:$C$16,MATCH(F80,Settings!$A$11:$A$16,0)) -> 0.5 | K80: =I80*J80 -> 25000 | L80: 46326 | M80: =Settings!$B$3-DATE(2026,9,17) -> 0 | N80: 46282 | O80: Alex Burrows | P80: Food & Beverage | Q80: Beer | R80: damm.com
A81: Ashley Madison | B81: Ashley Madison | C81: Ritchie Boubouli | D81: Levi Hoang | E81: Existing client | F81: Create Proposal | G81: 60000 | H81: USD | I81: =G81*INDEX(Settings!$B$6:$B$8,MATCH(H81,Settings!$A$6:$A$8,0)) -> 44400 | J81: =INDEX(Settings!$C$11:$C$16,MATCH(F81,Settings!$A$11:$A$16,0)) -> 0.5 | K81: =I81*J81 -> 22200 | L81: 46295 | M81: =Settings!$B$3-DATE(2026,9,1) -> 16 | N81: 46266 | O81: rebekah.kordich | P81: Tech | Q81: Dating App | R81: ashleymadison.com
A82: Curias | B82: Curias SOW 1 - SEP 26 | C82: Carrick Klopper | D82: - | E82: New business | F82: Create Proposal | G82: 60000 | H82: USD | I82: =G82*INDEX(Settings!$B$6:$B$8,MATCH(H82,Settings!$A$6:$A$8,0)) -> 44400 | J82: =INDEX(Settings!$C$11:$C$16,MATCH(F82,Settings!$A$11:$A$16,0)) -> 0.5 | K82: =I82*J82 -> 22200 | L82: 46326 | M82: =Settings!$B$3-DATE(2026,9,14) -> 3 | N82: 46279 | O82: Woojin Lim | R82: curias.io
A83: NN Spain | B83: NN Spain | C83: Ritchie Boubouli | D83: - | E83: Existing client | F83: Create Proposal | G83: 45000 | H83: EUR | I83: =G83*INDEX(Settings!$B$6:$B$8,MATCH(H83,Settings!$A$6:$A$8,0)) -> 38250 | J83: =INDEX(Settings!$C$11:$C$16,MATCH(F83,Settings!$A$11:$A$16,0)) -> 0.5 | K83: =I83*J83 -> 19125 | L83: 46290 | M83: =Settings!$B$3-DATE(2026,9,1) -> 16 | N83: 46266 | O83: carolina.corti | P83: Finance | Q83: Insurance | R83: nnespana.es
A84: Kenvue | B84: Kenvue | C84: Ritchie Boubouli | D84: - | E84: New business | F84: Create Proposal | G84: 50000 | H84: USD | I84: =G84*INDEX(Settings!$B$6:$B$8,MATCH(H84,Settings!$A$6:$A$8,0)) -> 37000 | J84: =INDEX(Settings!$C$11:$C$16,MATCH(F84,Settings!$A$11:$A$16,0)) -> 0.5 | K84: =I84*J84 -> 18500 | L84: 46374 | M84: =Settings!$B$3-DATE(2026,7,10) -> 69 | N84: 46212 | O84: Mark Cibort | P84: CPG | Q84: Consumer Health | R84: kenvue.com
A85: Go Pro | B85: Go Pro x TikTok Marketing Campaign | C85: Ritchie Boubouli | D85: Lucia Lopez Moreno | E85: Existing client | F85: Create Proposal | G85: 50000 | H85: USD | I85: =G85*INDEX(Settings!$B$6:$B$8,MATCH(H85,Settings!$A$6:$A$8,0)) -> 37000 | J85: =INDEX(Settings!$C$11:$C$16,MATCH(F85,Settings!$A$11:$A$16,0)) -> 0.5 | K85: =I85*J85 -> 18500 | L85: 46295 | M85: =Settings!$B$3-DATE(2026,7,10) -> 69 | N85: 46213 | O85: Rick Loughery | P85: Tech | Q85: Consumer Electronics | R85: gopro.com
A86: Norweigan Log | B86: Norweigan Log | C86: Ritchie Boubouli | D86: - | E86: New business | F86: Create Proposal | G86: 30000 | H86: GBP | I86: =G86*INDEX(Settings!$B$6:$B$8,MATCH(H86,Settings!$A$6:$A$8,0)) -> 30000 | J86: =INDEX(Settings!$C$11:$C$16,MATCH(F86,Settings!$A$11:$A$16,0)) -> 0.5 | K86: =I86*J86 -> 15000 | L86: 46276 | M86: =Settings!$B$3-DATE(2026,8,16) -> 32 | N86: 46250 | O86: ed taylor | P86: Retail | Q86: Log Cabins & Garden Rooms | R86: norwegianlog.co.uk
A87: RedWeek | B87: RedWeek - TLB | C87: Valeriia Mukhai | D87: - | E87: New business | F87: Create Proposal | G87: 35000 | H87: USD | I87: =G87*INDEX(Settings!$B$6:$B$8,MATCH(H87,Settings!$A$6:$A$8,0)) -> 25900 | J87: =INDEX(Settings!$C$11:$C$16,MATCH(F87,Settings!$A$11:$A$16,0)) -> 0.5 | K87: =I87*J87 -> 12950 | L87: 46356 | M87: =Settings!$B$3-DATE(2026,9,9) -> 8 | N87: 46274 | O87: Drew Minert | P87: Travel & Telecom | Q87: Timeshare Rentals | R87: redweek.com
A88: Trip | B88: Trip SOW 1 - NOV 26 | C88: Carrick Klopper | D88: - | E88: Existing client | F88: Create Proposal | G88: 30000 | H88: EUR | I88: =G88*INDEX(Settings!$B$6:$B$8,MATCH(H88,Settings!$A$6:$A$8,0)) -> 25500 | J88: =INDEX(Settings!$C$11:$C$16,MATCH(F88,Settings!$A$11:$A$16,0)) -> 0.5 | K88: =I88*J88 -> 12750 | L88: 46356 | M88: =Settings!$B$3-DATE(2026,9,17) -> 0 | N88: 46282 | O88: Selima Faye | P88: Travel & Telecom | Q88: OTA / Travel Platform | R88: trip.com
A89: KOTRA Atlanta | B89: KOTRA Atlanta - Brand #3 / September | C89: Valeriia Mukhai | D89: Maggie Parrott | E89: Existing client | F89: Create Proposal | G89: 30000 | H89: USD | I89: =G89*INDEX(Settings!$B$6:$B$8,MATCH(H89,Settings!$A$6:$A$8,0)) -> 22200 | J89: =INDEX(Settings!$C$11:$C$16,MATCH(F89,Settings!$A$11:$A$16,0)) -> 0.5 | K89: =I89*J89 -> 11100 | L89: 46290 | M89: =Settings!$B$3-DATE(2026,9,10) -> 7 | N89: 46252 | O89: Seonlim Lee | P89: CPG | Q89: Korean Beauty (KOTRA programme) | R89: kotra.or.kr
A90: GSMA | B90: GSMA SOW 1 - OCT 26 | C90: Carrick Klopper | D90: - | E90: New business | F90: Create Proposal | G90: 20000 | H90: GBP | I90: =G90*INDEX(Settings!$B$6:$B$8,MATCH(H90,Settings!$A$6:$A$8,0)) -> 20000 | J90: =INDEX(Settings!$C$11:$C$16,MATCH(F90,Settings!$A$11:$A$16,0)) -> 0.5 | K90: =I90*J90 -> 10000 | L90: 46326 | M90: =Settings!$B$3-DATE(2026,3,19) -> 182 | N90: 46100 | O90: Justin Paul | P90: Travel & Telecom | Q90: Mobile Industry Association | R90: gsma.com
A91: Ashley Madison | B91: Ashley Madison [UGC Deal] | C91: Ritchie Boubouli | D91: Levi Hoang | E91: Existing client | F91: Create Proposal | G91: 25000 | H91: USD | I91: =G91*INDEX(Settings!$B$6:$B$8,MATCH(H91,Settings!$A$6:$A$8,0)) -> 18500 | J91: =INDEX(Settings!$C$11:$C$16,MATCH(F91,Settings!$A$11:$A$16,0)) -> 0.5 | K91: =I91*J91 -> 9250 | M91: =Settings!$B$3-DATE(2026,9,2) -> 15 | N91: 46267 | O91: rebekah.kordich | P91: Tech | Q91: Dating App | R91: ashleymadison.com
A92: Bimbo Bakeries USA (Grupo Bimbo) | B92: Bimbo Bakeries USA - Orowheat / Pilot Introduction | C92: Valeriia Mukhai | D92: - | E92: New business | F92: Create Proposal | G92: 20000 | H92: USD | I92: =G92*INDEX(Settings!$B$6:$B$8,MATCH(H92,Settings!$A$6:$A$8,0)) -> 14800 | J92: =INDEX(Settings!$C$11:$C$16,MATCH(F92,Settings!$A$11:$A$16,0)) -> 0.5 | K92: =I92*J92 -> 7400 | L92: 46387 | M92: =Settings!$B$3-DATE(2026,9,11) -> 6 | N92: 46276 | O92: Dante Treglio | P92: Food & Beverage | Q92: Bakery | R92: grupobimbo.com
A93: Atlas Capture | B93: Atlas Capture - POV Creator Pilot / 6 markets / 1 month | C93: Valeriia Mukhai | D93: - | E93: New business | F93: Create Proposal | G93: 20000 | H93: USD | I93: =G93*INDEX(Settings!$B$6:$B$8,MATCH(H93,Settings!$A$6:$A$8,0)) -> 14800 | J93: =INDEX(Settings!$C$11:$C$16,MATCH(F93,Settings!$A$11:$A$16,0)) -> 0.5 | K93: =I93*J93 -> 7400 | L93: 46295 | M93: =Settings!$B$3-DATE(2026,9,14) -> 3 | N93: 46279 | O93: Elijah Jupiter | P93: Tech | Q93: AI Training Data | R93: atlascapture.io
A94: HEYTEA | B94: HEYTEA - Australia | C94: Ritchie Boubouli | D94: Levi Hoang | E94: Existing client | F94: Create Proposal | G94: 10000 | H94: USD | I94: =G94*INDEX(Settings!$B$6:$B$8,MATCH(H94,Settings!$A$6:$A$8,0)) -> 7400 | J94: =INDEX(Settings!$C$11:$C$16,MATCH(F94,Settings!$A$11:$A$16,0)) -> 0.5 | K94: =I94*J94 -> 3700 | L94: 46297 | M94: =Settings!$B$3-DATE(2026,9,2) -> 15 | N94: 46267 | O94: Delia Chen | P94: Food & Beverage | Q94: Tea Chain | R94: heytea.com
A95: vinted | B95: Vinted x UGC Content Creation for Paid Ads | C95: Ritchie Boubouli | D95: Lucia Lopez Moreno | E95: Existing client | F95: Create Proposal | G95: 6000 | H95: GBP | I95: =G95*INDEX(Settings!$B$6:$B$8,MATCH(H95,Settings!$A$6:$A$8,0)) -> 6000 | J95: =INDEX(Settings!$C$11:$C$16,MATCH(F95,Settings!$A$11:$A$16,0)) -> 0.5 | K95: =I95*J95 -> 3000 | L95: 46290 | M95: =Settings!$B$3-DATE(2026,9,1) -> 16 | N95: 46266 | O95: keesha.khraud@vinted.com | P95: Tech | Q95: Online Marketplace | R95: vinted.com
A96: NVA | B96: NVA - TLB | C96: Valeriia Mukhai | D96: - | E96: New business | F96: Create Proposal | G96: 0 | H96: USD | I96: =G96*INDEX(Settings!$B$6:$B$8,MATCH(H96,Settings!$A$6:$A$8,0)) -> 0 | J96: =INDEX(Settings!$C$11:$C$16,MATCH(F96,Settings!$A$11:$A$16,0)) -> 0.5 | K96: =I96*J96 -> 0 | L96: 46387 | M96: =Settings!$B$3-DATE(2026,9,10) -> 7 | N96: 46274 | O96: Julia Healey | P96: Healthcare | Q96: Veterinary Care | R96: nva.com
A97: Hapimag AG | B97: Hapimag - New Channel Test (YouTube / Spotify / Podcast) / 2027 budget | C97: Valeriia Mukhai | D97: - | E97: New business | F97: Create Proposal | G97: 0 | H97: EUR | I97: =G97*INDEX(Settings!$B$6:$B$8,MATCH(H97,Settings!$A$6:$A$8,0)) -> 0 | J97: =INDEX(Settings!$C$11:$C$16,MATCH(F97,Settings!$A$11:$A$16,0)) -> 0.5 | K97: =I97*J97 -> 0 | L97: 46356 | M97: =Settings!$B$3-DATE(2026,9,15) -> 2 | N97: 46280 | O97: Irina Gorskaia | P97: Hospitality | Q97: Holiday Resorts | R97: hapimag.com
A98: Runway | B98: Runway - SOW3 / 6-month renewal (2027 projection) | C98: Valeriia Mukhai | D98: Emma-Leigh Pedder | E98: Existing client | F98: Understand Need/Problem | G98: 600000 | H98: USD | I98: =G98*INDEX(Settings!$B$6:$B$8,MATCH(H98,Settings!$A$6:$A$8,0)) -> 444000 | J98: =INDEX(Settings!$C$11:$C$16,MATCH(F98,Settings!$A$11:$A$16,0)) -> 0.45 | K98: =I98*J98 -> 199800 | L98: 46387 | M98: =Settings!$B$3-DATE(2026,8,31) -> 17 | N98: 46252 | O98: Julia Martins | P98: Tech | Q98: AI Video | R98: runwayml.com
A99: Olymptrade | B99: Q4 x Olymptrade x Infliuencer Marketing Campaign | C99: Ritchie Boubouli | D99: - | E99: Existing client | F99: Understand Need/Problem | G99: 200000 | H99: GBP | I99: =G99*INDEX(Settings!$B$6:$B$8,MATCH(H99,Settings!$A$6:$A$8,0)) -> 200000 | J99: =INDEX(Settings!$C$11:$C$16,MATCH(F99,Settings!$A$11:$A$16,0)) -> 0.45 | K99: =I99*J99 -> 90000 | L99: 46325 | M99: =Settings!$B$3-DATE(2026,8,19) -> 29 | N99: 46253 | O99: Olya | P99: Finance | Q99: Online Trading | R99: olymptrade.com
A100: Beauty of Joseon | B100: Beauty of Joseon - Holiday Campaign / December | C100: Valeriia Mukhai | D100: Maggie Parrott | E100: Existing client | F100: Understand Need/Problem | G100: 100000 | H100: GBP | I100: =G100*INDEX(Settings!$B$6:$B$8,MATCH(H100,Settings!$A$6:$A$8,0)) -> 100000 | J100: =INDEX(Settings!$C$11:$C$16,MATCH(F100,Settings!$A$11:$A$16,0)) -> 0.45 | K100: =I100*J100 -> 45000 | L100: 46356 | M100: =Settings!$B$3-DATE(2026,8,18) -> 30 | N100: 46252 | O100: ezly | P100: CPG | Q100: Korean Beauty | R100: beautyofjoseon.com
...

Sheet Brands
A1: Brand | B1: Client status | C1: Industry | D1: Sub-industry | E1: Website | F1: Open deals | G1: Pipeline (£) | H1: Furthest stage | I1: Account Owner | J1: Account Manager | K1: Contacts
A2: Kia | B2: New business | C2: Automotive | D2: Car Manufacturer | E2: kia.com | F2: =COUNTIF('Open Deals'!$A$2:$A$130,A2) -> 1 | G2: =SUMIF('Open Deals'!$A$2:$A$130,A2,'Open Deals'!$I$2:$I$130) -> 740000 | H2: =INDEX(Settings!$A$11:$A$16,SUMPRODUCT(MAX((COUNTIFS('Open Deals'!$A$2:$A$130,A2,'Open Deals'!$F$2:$F$130,Settings!$A$11:$A$16)>0)*Settings!$B$11:$B$16))) -> Create Proposal | I2: Valeriia Mukhai | J2: - | K2: Ahreum Jang
A3: Runway | B3: Existing client | C3: Tech | D3: AI Video | E3: runwayml.com | F3: =COUNTIF('Open Deals'!$A$2:$A$130,A3) -> 2 | G3: =SUMIF('Open Deals'!$A$2:$A$130,A3,'Open Deals'!$I$2:$I$130) -> 666000 | H3: =INDEX(Settings!$A$11:$A$16,SUMPRODUCT(MAX((COUNTIFS('Open Deals'!$A$2:$A$130,A3,'Open Deals'!$F$2:$F$130,Settings!$A$11:$A$16)>0)*Settings!$B$11:$B$16))) -> IO Sent Out | I3: Valeriia Mukhai | J3: Emma-Leigh Pedder | K3: Julia Martins
A4: Beauty of Joseon | B4: Existing client | C4: CPG | D4: Korean Beauty | E4: beautyofjoseon.com | F4: =COUNTIF('Open Deals'!$A$2:$A$130,A4) -> 8 | G4: =SUMIF('Open Deals'!$A$2:$A$130,A4,'Open Deals'!$I$2:$I$130) -> 584500 | H4: =INDEX(Settings!$A$11:$A$16,SUMPRODUCT(MAX((COUNTIFS('Open Deals'!$A$2:$A$130,A4,'Open Deals'!$F$2:$F$130,Settings!$A$11:$A$16)>0)*Settings!$B$11:$B$16))) -> Negotiation | I4: Valeriia Mukhai | J4: Maggie Parrott | K4: ezly, haram
A5: Amorepacific | B5: Existing client | C5: CPG | D5: Korean Beauty | E5: amorepacific.com | F5: =COUNTIF('Open Deals'!$A$2:$A$130,A5) -> 4 | G5: =SUMIF('Open Deals'!$A$2:$A$130,A5,'Open Deals'!$I$2:$I$130) -> 293410 | H5: =INDEX(Settings!$A$11:$A$16,SUMPRODUCT(MAX((COUNTIFS('Open Deals'!$A$2:$A$130,A5,'Open Deals'!$F$2:$F$130,Settings!$A$11:$A$16)>0)*Settings!$B$11:$B$16))) -> IO Sent Out | I5: Valeriia Mukhai | J5: Maggie Parrott | K5: yeongeun, Judy - Jukyung Lee
A6: Mars Royal Canin | B6: Existing client | C6: CPG | D6: Pet Food | E6: royalcanin.com | F6: =COUNTIF('Open Deals'!$A$2:$A$130,A6) -> 2 | G6: =SUMIF('Open Deals'!$A$2:$A$130,A6,'Open Deals'!$I$2:$I$130) -> 287000 | H6: =INDEX(Settings!$A$11:$A$16,SUMPRODUCT(MAX((COUNTIFS('Open Deals'!$A$2:$A$130,A6,'Open Deals'!$F$2:$F$130,Settings!$A$11:$A$16)>0)*Settings!$B$11:$B$16))) -> Feedback | I6: Ritchie Boubouli | J6: Lucia Lopez Moreno | K6: riccarda Schmidt
A7: Webull Securities | B7: Existing client | C7: Finance | D7: Online Trading | E7: webull-uk.com | F7: =COUNTIF('Open Deals'!$A$2:$A$130,A7) -> 1 | G7: =SUMIF('Open Deals'!$A$2:$A$130,A7,'Open Deals'!$I$2:$I$130) -> 250000 | H7: =INDEX(Settings!$A$11:$A$16,SUMPRODUCT(MAX((COUNTIFS('Open Deals'!$A$2:$A$130,A7,'Open Deals'!$F$2:$F$130,Settings!$A$11:$A$16)>0)*Settings!$B$11:$B$16))) -> Feedback | I7: Ritchie Boubouli | J7: Levi Hoang | K7: Nick Saunders
A8: Oreate AI | B8: Existing client | C8: Tech | D8: AI | E8: oreateai.com | F8: =COUNTIF('Open Deals'!$A$2:$A$130,A8) -> 3 | G8: =SUMIF('Open Deals'!$A$2:$A$130,A8,'Open Deals'!$I$2:$I$130) -> 203500 | H8: =INDEX(Settings!$A$11:$A$16,SUMPRODUCT(MAX((COUNTIFS('Open Deals'!$A$2:$A$130,A8,'Open Deals'!$F$2:$F$130,Settings!$A$11:$A$16)>0)*Settings!$B$11:$B$16))) -> IO Sent Out | I8: Carrick Klopper | J8: Lucia Lopez Moreno | K8: Raul Tang
A9: Olymptrade | B9: Existing client | C9: Finance | D9: Online Trading | E9: olymptrade.com | F9: =COUNTIF('Open Deals'!$A$2:$A$130,A9) -> 1 | G9: =SUMIF('Open Deals'!$A$2:$A$130,A9,'Open Deals'!$I$2:$I$130) -> 200000 | H9: =INDEX(Settings!$A$11:$A$16,SUMPRODUCT(MAX((COUNTIFS('Open Deals'!$A$2:$A$130,A9,'Open Deals'!$F$2:$F$130,Settings!$A$11:$A$16)>0)*Settings!$B$11:$B$16))) -> Understand Need/Problem | I9: Ritchie Boubouli | J9: - | K9: Olya
A10: Konu Food Corp | B10: Existing client | C10: Food & Beverage | D10: Snacks | E10: konufoods.com | F10: =COUNTIF('Open Deals'!$A$2:$A$130,A10) -> 1 | G10: =SUMIF('Open Deals'!$A$2:$A$130,A10,'Open Deals'!$I$2:$I$130) -> 148000 | H10: =INDEX(Settings!$A$11:$A$16,SUMPRODUCT(MAX((COUNTIFS('Open Deals'!$A$2:$A$130,A10,'Open Deals'!$F$2:$F$130,Settings!$A$11:$A$16)>0)*Settings!$B$11:$B$16))) -> Create Proposal | I10: Ritchie Boubouli | J10: Lucia Lopez Moreno | K10: Patrick Paraguya
A11: Zonevoice | B11: New business | C11: Travel & Telecom | D11: eSIM App | E11: zonevoice.com | F11: =COUNTIF('Open Deals'!$A$2:$A$130,A11) -> 1 | G11: =SUMIF('Open Deals'!$A$2:$A$130,A11,'Open Deals'!$I$2:$I$130) -> 111000 | H11: =INDEX(Settings!$A$11:$A$16,SUMPRODUCT(MAX((COUNTIFS('Open Deals'!$A$2:$A$130,A11,'Open Deals'!$F$2:$F$130,Settings!$A$11:$A$16)>0)*Settings!$B$11:$B$16))) -> Negotiation | I11: Carrick Klopper | J11: - | K11: Marc Tanas
A12: Comfort Click | B12: Existing client | C12: Tech | D12: Smart Home | E12: comfortclick.co.uk | F12: =COUNTIF('Open Deals'!$A$2:$A$130,A12) -> 2 | G12: =SUMIF('Open Deals'!$A$2:$A$130,A12,'Open Deals'!$I$2:$I$130) -> 110000 | H12: =INDEX(Settings!$A$11:$A$16,SUMPRODUCT(MAX((COUNTIFS('Open Deals'!$A$2:$A$130,A12,'Open Deals'!$F$2:$F$130,Settings!$A$11:$A$16)>0)*Settings!$B$11:$B$16))) -> IO Sent Out | I12: Carrick Klopper | J12: - | K12: Prateek Tyagi
A13: FINOM | B13: Existing client | C13: Finance | D13: Fintech | E13: finom.co | F13: =COUNTIF('Open Deals'!$A$2:$A$130,A13) -> 3 | G13: =SUMIF('Open Deals'!$A$2:$A$130,A13,'Open Deals'!$I$2:$I$130) -> 105000 | H13: =INDEX(Settings!$A$11:$A$16,SUMPRODUCT(MAX((COUNTIFS('Open Deals'!$A$2:$A$130,A13,'Open Deals'!$F$2:$F$130,Settings!$A$11:$A$16)>0)*Settings!$B$11:$B$16))) -> Negotiation | I13: Valeriia Mukhai | J13: Emma-Leigh Pedder | K13: Aglaya Dvornikova
... A29: Byoma | B29: Existing client | C29: CPG | D29: Skincare | E29: byoma.com | F29: =COUNTIF('Open Deals'!$A$2:$A$130,A29) -> 1 | G29: =SUMIF('Open Deals'!$A$2:$A$130,A29,'Open Deals'!$I$2:$I$130) -> 74000 | H29: =INDEX(Settings!$A$11:$A$16,SUMPRODUCT(MAX((COUNTIFS('Open Deals'!$A$2:$A$130,A29,'Open Deals'!$F$2:$F$130,Settings!$A$11:$A$16)>0)*Settings!$B$11:$B$16))) -> Present Proposal | I29: Ritchie Boubouli | J29: Lucia Lopez Moreno | K29: Tara Loftis
A30: Quadthera | B30: Existing client | C30: Healthcare | D30: Biotech | F30: =COUNTIF('Open Deals'!$A$2:$A$130,A30) -> 1 | G30: =SUMIF('Open Deals'!$A$2:$A$130,A30,'Open Deals'!$I$2:$I$130) -> 74000 | H30: =INDEX(Settings!$A$11:$A$16,SUMPRODUCT(MAX((COUNTIFS('Open Deals'!$A$2:$A$130,A30,'Open Deals'!$F$2:$F$130,Settings!$A$11:$A$16)>0)*Settings!$B$11:$B$16))) -> Present Proposal | I30: Carrick Klopper | J30: - | K30: Andrew Park
A31: Opera Browser | B31: Existing client | C31: Tech | D31: SaaS | E31: opera.com | F31: =COUNTIF('Open Deals'!$A$2:$A$130,A31) -> 2 | G31: =SUMIF('Open Deals'!$A$2:$A$130,A31,'Open Deals'!$I$2:$I$130) -> 74000 | H31: =INDEX(Settings!$A$11:$A$16,SUMPRODUCT(MAX((COUNTIFS('Open Deals'!$A$2:$A$130,A31,'Open Deals'!$F$2:$F$130,Settings!$A$11:$A$16)>0)*Settings!$B$11:$B$16))) -> Present Proposal | I31: Valeriia Mukhai | J31: Emma-Leigh Pedder | K31: Shallana Santos
A32: Galderma | B32: Existing client | C32: Healthcare | D32: Dermatology / Pharma | E32: galderma.com | F32: =COUNTIF('Open Deals'!$A$2:$A$130,A32) -> 1 | G32: =SUMIF('Open Deals'!$A$2:$A$130,A32,'Open Deals'!$I$2:$I$130) -> 68000 | H32: =INDEX(Settings!$A$11:$A$16,SUMPRODUCT(MAX((COUNTIFS('Open Deals'!$A$2:$A$130,A32,'Open Deals'!$F$2:$F$130,Settings!$A$11:$A$16)>0)*Settings!$B$11:$B$16))) -> Feedback | I32: Ritchie Boubouli | J32: Sarineh Garapetian | K32: monika lamparska kania
A33: Monogram AI, Inc. | B33: New business | C33: Tech | D33: AI Consumer App | E33: monogram.ai | F33: =COUNTIF('Open Deals'!$A$2:$A$130,A33) -> 1 | G33: =SUMIF('Open Deals'!$A$2:$A$130,A33,'Open Deals'!$I$2:$I$130) -> 66600 | H33: =INDEX(Settings!$A$11:$A$16,SUMPRODUCT(MAX((COUNTIFS('Open Deals'!$A$2:$A$130,A33,'Open Deals'!$F$2:$F$130,Settings!$A$11:$A$16)>0)*Settings!$B$11:$B$16))) -> Feedback | I33: Carrick Klopper | J33: - | K33: EREN BALI
A34: BiteLab | B34: Existing client | C34: CPG | D34: Korean Beauty | E34: bitelab.co.kr | F34: =COUNTIF('Open Deals'!$A$2:$A$130,A34) -> 2 | G34: =SUMIF('Open Deals'!$A$2:$A$130,A34,'Open Deals'!$I$2:$I$130) -> 63640 | H34: =INDEX(Settings!$A$11:$A$16,SUMPRODUCT(MAX((COUNTIFS('Open Deals'!$A$2:$A$130,A34,'Open Deals'!$F$2:$F$130,Settings!$A$11:$A$16)>0)*Settings!$B$11:$B$16))) -> Negotiation | I34: Valeriia Mukhai | J34: Emma-Leigh Pedder | K34: gaby.ham
A35: Ashley Madison | B35: Existing client | C35: Tech | D35: Dating App | E35: ashleymadison.com | F35: =COUNTIF('Open Deals'!$A$2:$A$130,A35) -> 2 | G35: =SUMIF('Open Deals'!$A$2:$A$130,A35,'Open Deals'!$I$2:$I$130) -> 62900 | H35: =INDEX(Settings!$A$11:$A$16,SUMPRODUCT(MAX((COUNTIFS('Open Deals'!$A$2:$A$130,A35,'Open Deals'!$F$2:$F$130,Settings!$A$11:$A$16)>0)*Settings!$B$11:$B$16))) -> Create Proposal | I35: Ritchie Boubouli | J35: Levi Hoang | K35: rebekah.kordich
A36: Neals Yard Remedies | B36: Existing client | C36: CPG | D36: Beauty | E36: nealsyardremedies.com | F36: =COUNTIF('Open Deals'!$A$2:$A$130,A36) -> 1 | G36: =SUMIF('Open Deals'!$A$2:$A$130,A36,'Open Deals'!$I$2:$I$130) -> 60000 | H36: =INDEX(Settings!$A$11:$A$16,SUMPRODUCT(MAX((COUNTIFS('Open Deals'!$A$2:$A$130,A36,'Open Deals'!$F$2:$F$130,Settings!$A$11:$A$16)>0)*Settings!$B$11:$B$16))) -> Feedback | I36: Ritchie Boubouli | J36: - | K36: Goh
A37: David Lloyd Leisure | B37: New business | C37: Health & Wellness | D37: Gyms & Leisure Clubs | E37: davidlloyd.co.uk | F37: =COUNTIF('Open Deals'!$A$2:$A$130,A37) -> 1 | G37: =SUMIF('Open Deals'!$A$2:$A$130,A37,'Open Deals'!$I$2:$I$130) -> 60000 | H37: =INDEX(Settings!$A$11:$A$16,SUMPRODUCT(MAX((COUNTIFS('Open Deals'!$A$2:$A$130,A37,'Open Deals'!$F$2:$F$130,Settings!$A$11:$A$16)>0)*Settings!$B$11:$B$16))) -> Understand Need/Problem | I37: Ritchie Boubouli | J37: - | K37: james.burton-lee
A38: Sam'U | B38: Existing client | C38: CPG | D38: Korean Beauty | E38: samchic.co.kr | F38: =COUNTIF('Open Deals'!$A$2:$A$130,A38) -> 1 | G38: =SUMIF('Open Deals'!$A$2:$A$130,A38,'Open Deals'!$I$2:$I$130) -> 51800 | H38: =INDEX(Settings!$A$11:$A$16,SUMPRODUCT(MAX((COUNTIFS('Open Deals'!$A$2:$A$130,A38,'Open Deals'!$F$2:$F$130,Settings!$A$11:$A$16)>0)*Settings!$B$11:$B$16))) -> Negotiation | I38: Valeriia Mukhai | J38: Maggie Parrott | K38: jjk
A39: Astrotalk | B39: Existing client | C39: Tech | D39: Astrology App | E39: astrotalk.com | F39: =COUNTIF('Open Deals'!$A$2:$A$130,A39) -> 2 | G39: =SUMIF('Open Deals'!$A$2:$A$130,A39,'Open Deals'!$I$2:$I$130) -> 51800 | H39: =INDEX(Settings!$A$11:$A$16,SUMPRODUCT(MAX((COUNTIFS('Open Deals'!$A$2:$A$130,A39,'Open Deals'!$F$2:$F$130,Settings!$A$11:$A$16)>0)*Settings!$B$11:$B$16))) -> Negotiation | I39: Carrick Klopper | J39: Lucia Lopez Moreno | K39: Ishita Saxena
A40: SEB | B40: Existing client | C40: CPG | D40: Home Appliances | E40: groupeseb.com | F40: =COUNTIF('Open Deals'!$A$2:$A$130,A40) -> 1 | G40: =SUMIF('Open Deals'!$A$2:$A$130,A40,'Open Deals'!$I$2:$I$130) -> 51000 | H40: =INDEX(Settings!$A$11:$A$16,SUMPRODUCT(MAX((COUNTIFS('Open Deals'!$A$2:$A$130,A40,'Open Deals'!$F$2:$F$130,Settings!$A$11:$A$16)>0)*Settings!$B$11:$B$16))) -> IO Sent Out | I40: Ritchie Boubouli | J40: Sarineh Garapetian | K40: Paulina Gardunorubi
A41: Chill Sim | B41: New business | C41: Travel & Telecom | D41: eSIM App | E41: chillsim.net | F41: =COUNTIF('Open Deals'!$A$2:$A$130,A41) -> 1 | G41: =SUMIF('Open Deals'!$A$2:$A$130,A41,'Open Deals'!$I$2:$I$130) -> 51000 | H41: =INDEX(Settings!$A$11:$A$16,SUMPRODUCT(MAX((COUNTIFS('Open Deals'!$A$2:$A$130,A41,'Open Deals'!$F$2:$F$130,Settings!$A$11:$A$16)>0)*Settings!$B$11:$B$16))) -> Understand Need/Problem | I41: Carrick Klopper | J41: - | K41: Alexandru
A42: Medihealcos | B42: Existing client | C42: CPG | D42: Korean Beauty | E42: mediheal.com | F42: =COUNTIF('Open Deals'!$A$2:$A$130,A42) -> 1 | G42: =SUMIF('Open Deals'!$A$2:$A$130,A42,'Open Deals'!$I$2:$I$130) -> 50000 | H42: =INDEX(Settings!$A$11:$A$16,SUMPRODUCT(MAX((COUNTIFS('Open Deals'!$A$2:$A$130,A42,'Open Deals'!$F$2:$F$130,Settings!$A$11:$A$16)>0)*Settings!$B$11:$B$16))) -> IO Sent Out | I42: Valeriia Mukhai | J42: - | K42: hwjang
... A45: TeamSport | B45: New business | C45: Entertainment | D45: Indoor Go-Karting | E45: team-sport.com | F45: =COUNTIF('Open Deals'!$A$2:$A$130,A45) -> 1 | G45: =SUMIF('Open Deals'!$A$2:$A$130,A45,'Open Deals'!$I$2:$I$130) -> 45000 | H45: =INDEX(Settings!$A$11:$A$16,SUMPRODUCT(MAX((COUNTIFS('Open Deals'!$A$2:$A$130,A45,'Open Deals'!$F$2:$F$130,Settings!$A$11:$A$16)>0)*Settings!$B$11:$B$16))) -> Negotiation | I45: Carrick Klopper | J45: - | K45: Angela Porter
A46: Myungin Cosmetics (Farmstay / Anotherface / Laferme) | B46: New business | C46: CPG | D46: Korean Beauty | F46: =COUNTIF('Open Deals'!$A$2:$A$130,A46) -> 1 | G46: =SUMIF('Open Deals'!$A$2:$A$130,A46,'Open Deals'!$I$2:$I$130) -> 44400 | H46: =INDEX(Settings!$A$11:$A$16,SUMPRODUCT(MAX((COUNTIFS('Open Deals'!$A$2:$A$130,A46,'Open Deals'!$F$2:$F$130,Settings!$A$11:$A$16)>0)*Settings!$B$11:$B$16))) -> IO Sent Out | I46: Valeriia Mukhai | J46: - | K46: Seonlim Lee
A47: Viora | B47: Existing client | C47: Healthcare | D47: FemTech Diagnostics | E47: vioratest.com | F47: =COUNTIF('Open Deals'!$A$2:$A$130,A47) -> 1 | G47: =SUMIF('Open Deals'!$A$2:$A$130,A47,'Open Deals'!$I$2:$I$130) -> 44400 | H47: =INDEX(Settings!$A$11:$A$16,SUMPRODUCT(MAX((COUNTIFS('Open Deals'!$A$2:$A$130,A47,'Open Deals'!$F$2:$F$130,Settings!$A$11:$A$16)>0)*Settings!$B$11:$B$16))) -> Feedback | I47: Ritchie Boubouli | J47: Lucia Lopez Moreno | K47: Michael McDade
A48: Amplify Ventures Ltd. | B48: New business | C48: Travel & Telecom | D48: eSIM App | E48: studiomosaicapps.com | F48: =COUNTIF('Open Deals'!$A$2:$A$130,A48) -> 1 | G48: =SUMIF('Open Deals'!$A$2:$A$130,A48,'Open Deals'!$I$2:$I$130) -> 44400 | H48: =INDEX(Settings!$A$11:$A$16,SUMPRODUCT(MAX((COUNTIFS('Open Deals'!$A$2:$A$130,A48,'Open Deals'!$F$2:$F$130,Settings!$A$11:$A$16)>0)*Settings!$B$11:$B$16))) -> Feedback | I48: Carrick Klopper | J48: - | K48: Ishita Chaudhary
A49: Skylum | B49: Existing client | C49: Tech | D49: Creative SaaS | E49: skylum.com | F49: =COUNTIF('Open Deals'!$A$2:$A$130,A49) -> 1 | G49: =SUMIF('Open Deals'!$A$2:$A$130,A49,'Open Deals'!$I$2:$I$130) -> 44400 | H49: =INDEX(Settings!$A$11:$A$16,SUMPRODUCT(MAX((COUNTIFS('Open Deals'!$A$2:$A$130,A49,'Open Deals'!$F$2:$F$130,Settings!$A$11:$A$16)>0)*Settings!$B$11:$B$16))) -> Present Proposal | I49: Valeriia Mukhai | J49: - | K49: Kateryna Medushyvska
A50: Curias | B50: New business | E50: curias.io | F50: =COUNTIF('Open Deals'!$A$2:$A$130,A50) -> 1 | G50: =SUMIF('Open Deals'!$A$2:$A$130,A50,'Open Deals'!$I$2:$I$130) -> 44400 | H50: =INDEX(Settings!$A$11:$A$16,SUMPRODUCT(MAX((COUNTIFS('Open Deals'!$A$2:$A$130,A50,'Open Deals'!$F$2:$F$130,Settings!$A$11:$A$16)>0)*Settings!$B$11:$B$16))) -> Create Proposal | I50: Carrick Klopper | J50: - | K50: Woojin Lim
A51: Medtrition, Inc. | B51: New business | C51: Healthcare | D51: Medical Nutrition | E51: medtrition.com | F51: =COUNTIF('Open Deals'!$A$2:$A$130,A51) -> 1 | G51: =SUMIF('Open Deals'!$A$2:$A$130,A51,'Open Deals'!$I$2:$I$130) -> 44400 | H51: =INDEX(Settings!$A$11:$A$16,SUMPRODUCT(MAX((COUNTIFS('Open Deals'!$A$2:$A$130,A51,'Open Deals'!$F$2:$F$130,Settings!$A$11:$A$16)>0)*Settings!$B$11:$B$16))) -> Understand Need/Problem | I51: Valeriia Mukhai | J51: - | K51: Megan Koons
A52: NN Spain | B52: Existing client | C52: Finance | D52: Insurance | E52: nnespana.es | F52: =COUNTIF('Open Deals'!$A$2:$A$130,A52) -> 1 | G52: =SUMIF('Open Deals'!$A$2:$A$130,A52,'Open Deals'!$I$2:$I$130) -> 38250 | H52: =INDEX(Settings!$A$11:$A$16,SUMPRODUCT(MAX((COUNTIFS('Open Deals'!$A$2:$A$130,A52,'Open Deals'!$F$2:$F$130,Settings!$A$11:$A$16)>0)*Settings!$B$11:$B$16))) -> Create Proposal | I52: Ritchie Boubouli | J52: - | K52: carolina.corti
A53: Dumbbell's Incorporated | B53: New business | F53: =COUNTIF('Open Deals'!$A$2:$A$130,A53) -> 1 | G53: =SUMIF('Open Deals'!$A$2:$A$130,A53,'Open Deals'!$I$2:$I$130) -> 37000 | H53: =INDEX(Settings!$A$11:$A$16,SUMPRODUCT(MAX((COUNTIFS('Open Deals'!$A$2:$A$130,A53,'Open Deals'!$F$2:$F$130,Settings!$A$11:$A$16)>0)*Settings!$B$11:$B$16))) -> Negotiation | I53: Carrick Klopper | J53: - | K53: Bob Barreca
A54: I-World | B54: New business | C54: CPG | D54: Korean Beauty | E54: iworldus.com | F54: =COUNTIF('Open Deals'!$A$2:$A$130,A54) -> 1 | G54: =SUMIF('Open Deals'!$A$2:$A$130,A54,'Open Deals'!$I$2:$I$130) -> 37000 | H54: =INDEX(Settings!$A$11:$A$16,SUMPRODUCT(MAX((COUNTIFS('Open Deals'!$A$2:$A$130,A54,'Open Deals'!$F$2:$F$130,Settings!$A$11:$A$16)>0)*Settings!$B$11:$B$16))) -> Negotiation | I54: Valeriia Mukhai | J54: - | K54: Daniel Yi
A55: THE RIVIERA | B55: New business | C55: CPG | D55: Fragrance Mists | E55: riviera-dazur.com | F55: =COUNTIF('Open Deals'!$A$2:$A$130,A55) -> 1 | G55: =SUMIF('Open Deals'!$A$2:$A$130,A55,'Open Deals'!$I$2:$I$130) -> 37000 | H55: =INDEX(Settings!$A$11:$A$16,SUMPRODUCT(MAX((COUNTIFS('Open Deals'!$A$2:$A$130,A55,'Open Deals'!$F$2:$F$130,Settings!$A$11:$A$16)>0)*Settings!$B$11:$B$16))) -> Feedback | I55: Valeriia Mukhai | J55: - | K55: Heejae Choi
A56: mary browns | B56: Existing client | C56: Food & Beverage | D56: QSR / Fast Food | E56: mbchicken.co.uk | F56: =COUNTIF('Open Deals'!$A$2:$A$130,A56) -> 1 | G56: =SUMIF('Open Deals'!$A$2:$A$130,A56,'Open Deals'!$I$2:$I$130) -> 37000 | H56: =INDEX(Settings!$A$11:$A$16,SUMPRODUCT(MAX((COUNTIFS('Open Deals'!$A$2:$A$130,A56,'Open Deals'!$F$2:$F$130,Settings!$A$11:$A$16)>0)*Settings!$B$11:$B$16))) -> Present Proposal | I56: Ritchie Boubouli | J56: Levi Hoang | K56: michelle payot
A57: I-ne Co., Ltd. | B57: New business | C57: CPG | D57: Japanese Beauty / Haircare | E57: i-ne.co.jp | F57: =COUNTIF('Open Deals'!$A$2:$A$130,A57) -> 1 | G57: =SUMIF('Open Deals'!$A$2:$A$130,A57,'Open Deals'!$I$2:$I$130) -> 37000 | H57: =INDEX(Settings!$A$11:$A$16,SUMPRODUCT(MAX((COUNTIFS('Open Deals'!$A$2:$A$130,A57,'Open Deals'!$F$2:$F$130,Settings!$A$11:$A$16)>0)*Settings!$B$11:$B$16))) -> Present Proposal | I57: Valeriia Mukhai | J57: - | K57: Lilia Yamakawa
A58: Kenvue | B58: New business | C58: CPG | D58: Consumer Health | E58: kenvue.com | F58: =COUNTIF('Open Deals'!$A$2:$A$130,A58) -> 1 | G58: =SUMIF('Open Deals'!$A$2:$A$130,A58,'Open Deals'!$I$2:$I$130) -> 37000 | H58: =INDEX(Settings!$A$11:$A$16,SUMPRODUCT(MAX((COUNTIFS('Open Deals'!$A$2:$A$130,A58,'Open Deals'!$F$2:$F$130,Settings!$A$11:$A$16)>0)*Settings!$B$11:$B$16))) -> Create Proposal | I58: Ritchie Boubouli | J58: - | K58: Mark Cibort
A59: Go Pro | B59: Existing client | C59: Tech | D59: Consumer Electronics | E59: gopro.com | F59: =COUNTIF('Open Deals'!$A$2:$A$130,A59) -> 1 | G59: =SUMIF('Open Deals'!$A$2:$A$130,A59,'Open Deals'!$I$2:$I$130) -> 37000 | H59: =INDEX(Settings!$A$11:$A$16,SUMPRODUCT(MAX((COUNTIFS('Open Deals'!$A$2:$A$130,A59,'Open Deals'!$F$2:$F$130,Settings!$A$11:$A$16)>0)*Settings!$B$11:$B$16))) -> Create Proposal | I59: Ritchie Boubouli | J59: Lucia Lopez Moreno | K59: Rick Loughery
A60: Kioland | B60: Existing client | C60: Tech | D60: E-commerce | E60: kioland.co.kr | F60: =COUNTIF('Open Deals'!$A$2:$A$130,A60) -> 1 | G60: =SUMIF('Open Deals'!$A$2:$A$130,A60,'Open Deals'!$I$2:$I$130) -> 37000 | H60: =INDEX(Settings!$A$11:$A$16,SUMPRODUCT(MAX((COUNTIFS('Open Deals'!$A$2:$A$130,A60,'Open Deals'!$F$2:$F$130,Settings!$A$11:$A$16)>0)*Settings!$B$11:$B$16))) -> Understand Need/Problem | I60: Carrick Klopper | J60: - | K60: Grace Lee
A61: The Picton | B61: Existing client | C61: Hospitality | D61: Hotel | E61: thepicton.com | F61: =COUNTIF('Open Deals'!$A$2:$A$130,A61) -> 1 | G61: =SUMIF('Open Deals'!$A$2:$A$130,A61,'Open Deals'!$I$2:$I$130) -> 37000 | H61: =INDEX(Settings!$A$11:$A$16,SUMPRODUCT(MAX((COUNTIFS('Open Deals'!$A$2:$A$130,A61,'Open Deals'!$F$2:$F$130,Settings!$A$11:$A$16)>0)*Settings!$B$11:$B$16))) -> Understand Need/Problem | I61: Valeriia Mukhai | J61: Maggie Parrott | K61: jiyeon
A62: Procter & Gamble | B62: New business | C62: CPG | D62: Personal Care | E62: pg.com | F62: =COUNTIF('Open Deals'!$A$2:$A$130,A62) -> 1 | G62: =SUMIF('Open Deals'!$A$2:$A$130,A62,'Open Deals'!$I$2:$I$130) -> 37000 | H62: =INDEX(Settings!$A$11:$A$16,SUMPRODUCT(MAX((COUNTIFS('Open Deals'!$A$2:$A$130,A62,'Open Deals'!$F$2:$F$130,Settings!$A$11:$A$16)>0)*Settings!$B$11:$B$16))) -> Understand Need/Problem | I62: Valeriia Mukhai | J62: - | K62: Hassna Machkour
A63: AvaTrade | B63: Existing client | C63: Finance | D63: Online Trading | E63: avatrade.com | F63: =COUNTIF('Open Deals'!$A$2:$A$130,A63) -> 2 | G63: =SUMIF('Open Deals'!$A$2:$A$130,A63,'Open Deals'!$I$2:$I$130) -> 33337 | H63: =INDEX(Settings!$A$11:$A$16,SUMPRODUCT(MAX((COUNTIFS('Open Deals'!$A$2:$A$130,A63,'Open Deals'!$F$2:$F$130,Settings!$A$11:$A$16)>0)*Settings!$B$11:$B$16))) -> IO Sent Out | I63: Ritchie Boubouli | J63: Lucia Lopez Moreno | K63: Nicolas Embon
A64: Firerock Capital | B64: New business | C64: Entertainment | D64: Mobile Game | E64: firerock.sg | F64: =COUNTIF('Open Deals'!$A$2:$A$130,A64) -> 1 | G64: =SUMIF('Open Deals'!$A$2:$A$130,A64,'Open Deals'!$I$2:$I$130) -> 33300 | H64: =INDEX(Settings!$A$11:$A$16,SUMPRODUCT(MAX((COUNTIFS('Open Deals'!$A$2:$A$130,A64,'Open Deals'!$F$2:$F$130,Settings!$A$11:$A$16)>0)*Settings!$B$11:$B$16))) -> Negotiation | I64: Carrick Klopper | J64: - | K64: June Kwa
A65: Norweigan Log | B65: New business | C65: Retail | D65: Log Cabins & Garden Rooms | E65: norwegianlog.co.uk | F65: =COUNTIF('Open Deals'!$A$2:$A$130,A65) -> 1 | G65: =SUMIF('Open Deals'!$A$2:$A$130,A65,'Open Deals'!$I$2:$I$130) -> 30000 | H65: =INDEX(Settings!$A$11:$A$16,SUMPRODUCT(MAX((COUNTIFS('Open Deals'!$A$2:$A$130,A65,'Open Deals'!$F$2:$F$130,Settings!$A$11:$A$16)>0)*Settings!$B$11:$B$16))) -> Create Proposal | I65: Ritchie Boubouli | J65: - | K65: ed taylor
A66: Peekboo | B66: New business | F66: =COUNTIF('Open Deals'!$A$2:$A$130,A66) -> 1 | G66: =SUMIF('Open Deals'!$A$2:$A$130,A66,'Open Deals'!$I$2:$I$130) -> 30000 | H66: =INDEX(Settings!$A$11:$A$16,SUMPRODUCT(MAX((COUNTIFS('Open Deals'!$A$2:$A$130,A66,'Open Deals'!$F$2:$F$130,Settings!$A$11:$A$16)>0)*Settings!$B$11:$B$16))) -> Understand Need/Problem | I66: Carrick Klopper | J66: - | K66: Jonathan Howells
A67: Fitness First | B67: New business | C67: Health & Wellness | D67: Gyms | E67: fitnessfirst.com | F67: =COUNTIF('Open Deals'!$A$2:$A$130,A67) -> 1 | G67: =SUMIF('Open Deals'!$A$2:$A$130,A67,'Open Deals'!$I$2:$I$130) -> 30000 | H67: =INDEX(Settings!$A$11:$A$16,SUMPRODUCT(MAX((COUNTIFS('Open Deals'!$A$2:$A$130,A67,'Open Deals'!$F$2:$F$130,Settings!$A$11:$A$16)>0)*Settings!$B$11:$B$16))) -> Understand Need/Problem | I67: Ritchie Boubouli | J67: - | K67: Lee Pinnington
A68: 111Skin | B68: New business | C68: CPG | D68: Skincare | E68: 111skin.com | F68: =COUNTIF('Open Deals'!$A$2:$A$130,A68) -> 1 | G68: =SUMIF('Open Deals'!$A$2:$A$130,A68,'Open Deals'!$I$2:$I$130) -> 30000 | H68: =INDEX(Settings!$A$11:$A$16,SUMPRODUCT(MAX((COUNTIFS('Open Deals'!$A$2:$A$130,A68,'Open Deals'!$F$2:$F$130,Settings!$A$11:$A$16)>0)*Settings!$B$11:$B$16))) -> Understand Need/Problem | I68: Ritchie Boubouli | J68: - | K68: Michael Edelmann
A69: Paddywax | B69: New business | C69: CPG | D69: Home Fragrance | E69: paddywax.com | F69: =COUNTIF('Open Deals'!$A$2:$A$130,A69) -> 1 | G69: =SUMIF('Open Deals'!$A$2:$A$130,A69,'Open Deals'!$I$2:$I$130) -> 29600 | H69: =INDEX(Settings!$A$11:$A$16,SUMPRODUCT(MAX((COUNTIFS('Open Deals'!$A$2:$A$130,A69,'Open Deals'!$F$2:$F$130,Settings!$A$11:$A$16)>0)*Settings!$B$11:$B$16))) -> Negotiation | I69: Valeriia Mukhai | J69: - | K69: Alexi Mintz
A70: Vancouver Whitecaps FC | B70: New business | C70: Entertainment | D70: Football Club | E70: whitecapsfc.com | F70: =COUNTIF('Open Deals'!$A$2:$A$130,A70) -> 1 | G70: =SUMIF('Open Deals'!$A$2:$A$130,A70,'Open Deals'!$I$2:$I$130) -> 29600 | H70: =INDEX(Settings!$A$11:$A$16,SUMPRODUCT(MAX((COUNTIFS('Open Deals'!$A$2:$A$130,A70,'Open Deals'!$F$2:$F$130,Settings!$A$11:$A$16)>0)*Settings!$B$11:$B$16))) -> Present Proposal | I70: Carrick Klopper | J70: - | K70: Adam Ferreira
A71: AviaGames | B71: Existing client | C71: Entertainment | D71: Mobile Game | E71: aviagames.com | F71: =COUNTIF('Open Deals'!$A$2:$A$130,A71) -> 1 | G71: =SUMIF('Open Deals'!$A$2:$A$130,A71,'Open Deals'!$I$2:$I$130) -> 29600 | H71: =INDEX(Settings!$A$11:$A$16,SUMPRODUCT(MAX((COUNTIFS('Open Deals'!$A$2:$A$130,A71,'Open Deals'!$F$2:$F$130,Settings!$A$11:$A$16)>0)*Settings!$B$11:$B$16))) -> Understand Need/Problem | I71: Carrick Klopper | J71: Blake Hoang | K71: Chloe Zhang
A72: TFIT | B72: Existing client | C72: CPG | D72: Korean Beauty | E72: tfit.co.kr | F72: =COUNTIF('Open Deals'!$A$2:$A$130,A72) -> 2 | G72: =SUMIF('Open Deals'!$A$2:$A$130,A72,'Open Deals'!$I$2:$I$130) -> 28860 | H72: =INDEX(Settings!$A$11:$A$16,SUMPRODUCT(MAX((COUNTIFS('Open Deals'!$A$2:$A$130,A72,'Open Deals'!$F$2:$F$130,Settings!$A$11:$A$16)>0)*Settings!$B$11:$B$16))) -> IO Sent Out | I72: Valeriia Mukhai | J72: - | K72: Elly
A73: RedWeek | B73: New business | C73: Travel & Telecom | D73: Timeshare Rentals | E73: redweek.com | F73: =COUNTIF('Open Deals'!$A$2:$A$130,A73) -> 1 | G73: =SUMIF('Open Deals'!$A$2:$A$130,A73,'Open Deals'!$I$2:$I$130) -> 25900 | H73: =INDEX(Settings!$A$11:$A$16,SUMPRODUCT(MAX((COUNTIFS('Open Deals'!$A$2:$A$130,A73,'Open Deals'!$F$2:$F$130,Settings!$A$11:$A$16)>0)*Settings!$B$11:$B$16))) -> Create Proposal | I73: Valeriia Mukhai | J73: - | K73: Drew Minert
A74: Myntro | B74: New business | C74: Finance | D74: Debt Management | E74: myntro.com | F74: =COUNTIF('Open Deals'!$A$2:$A$130,A74) -> 1 | G74: =SUMIF('Open Deals'!$A$2:$A$130,A74,'Open Deals'!$I$2:$I$130) -> 25500 | H74: =INDEX(Settings!$A$11:$A$16,SUMPRODUCT(MAX((COUNTIFS('Open Deals'!$A$2:$A$130,A74,'Open Deals'!$F$2:$F$130,Settings!$A$11:$A$16)>0)*Settings!$B$11:$B$16))) -> Negotiation | I74: Carrick Klopper | J74: - | K74: Moa Tyborn
A75: Trip | B75: Existing client | C75: Travel & Telecom | D75: OTA / Travel Platform | E75: trip.com | F75: =COUNTIF('Open Deals'!$A$2:$A$130,A75) -> 1 | G75: =SUMIF('Open Deals'!$A$2:$A$130,A75,'Open Deals'!$I$2:$I$130) -> 25500 | H75: =INDEX(Settings!$A$11:$A$16,SUMPRODUCT(MAX((COUNTIFS('Open Deals'!$A$2:$A$130,A75,'Open Deals'!$F$2:$F$130,Settings!$A$11:$A$16)>0)*Settings!$B$11:$B$16))) -> Create Proposal | I75: Carrick Klopper | J75: - | K75: Selima Faye
A76: Aldermore | B76: New business | C76: Finance | D76: Bank | E76: aldermore.co.uk | F76: =COUNTIF('Open Deals'!$A$2:$A$130,A76) -> 1 | G76: =SUMIF('Open Deals'!$A$2:$A$130,A76,'Open Deals'!$I$2:$I$130) -> 25000 | H76: =INDEX(Settings!$A$11:$A$16,SUMPRODUCT(MAX((COUNTIFS('Open Deals'!$A$2:$A$130,A76,'Open Deals'!$F$2:$F$130,Settings!$A$11:$A$16)>0)*Settings!$B$11:$B$16))) -> Feedback | I76: Carrick Klopper | J76: - | K76: David Reynell
A77: BNC Korea | B77: Existing client | C77: Healthcare | D77: Biopharma / Aesthetics | E77: bnckorea.co.kr | F77: =COUNTIF('Open Deals'!$A$2:$A$130,A77) -> 1 | G77: =SUMIF('Open Deals'!$A$2:$A$130,A77,'Open Deals'!$I$2:$I$130) -> 22200 | H77: =INDEX(Settings!$A$11:$A$16,SUMPRODUCT(MAX((COUNTIFS('Open Deals'!$A$2:$A$130,A77,'Open Deals'!$F$2:$F$130,Settings!$A$11:$A$16)>0)*Settings!$B$11:$B$16))) -> Negotiation | I77: Carrick Klopper | J77: Blake Hoang | K77: hihong
A78: Pacsen | B78: New business | C78: Retail | D78: Sporting Goods OEM | E78: pacsen.net | F78: =COUNTIF('Open Deals'!$A$2:$A$130,A78) -> 1 | G78: =SUMIF('Open Deals'!$A$2:$A$130,A78,'Open Deals'!$I$2:$I$130) -> 22200 | H78: =INDEX(Settings!$A$11:$A$16,SUMPRODUCT(MAX((COUNTIFS('Open Deals'!$A$2:$A$130,A78,'Open Deals'!$F$2:$F$130,Settings!$A$11:$A$16)>0)*Settings!$B$11:$B$16))) -> Feedback | I78: Valeriia Mukhai | J78: - | K78: jason.suk
... A105: Two Poles | B105: New business | C105: CPG | D105: Skincare | E105: twopoles.co | F105: =COUNTIF('Open Deals'!$A$2:$A$130,A105) -> 1 | G105: =SUMIF('Open Deals'!$A$2:$A$130,A105,'Open Deals'!$I$2:$I$130) -> 0 | H105: =INDEX(Settings!$A$11:$A$16,SUMPRODUCT(MAX((COUNTIFS('Open Deals'!$A$2:$A$130,A105,'Open Deals'!$F$2:$F$130,Settings!$A$11:$A$16)>0)*Settings!$B$11:$B$16))) -> Understand Need/Problem | I105: Valeriia Mukhai | J105: - | K105: Laura Murcia

Sheet Settings
A1: Settings
A3: Report date | B3: 46282
A5: Currency | B5: Rate to GBP
A6: GBP | B6: 1
A7: USD | B7: 0.74
A8: EUR | B8: 0.85
A10: Stage | B10: Order | C10: Probability
A11: Understand Need/Problem | B11: 1 | C11: 0.45
A12: Create Proposal | B12: 2 | C12: 0.5
A13: Present Proposal | B13: 3 | C13: 0.55
A14: Feedback | B14: 4 | C14: 0.6
A15: Negotiation | B15: 5 | C15: 0.75
A16: IO Sent Out | B16: 6 | C16: 0.85
A18: Probability = Pipedrive stage default. Client status = "Existing client" if the brand has at least one won deal in Pipedrive.
